{
  "id": "allin1-stream",
  "name": "All In 1 Stream",
  "version": "V1.0",
  "color": "#1cb57a",
  "grid_number": 3,
  "description": "This file does not stream any of the included channels, all streaming links are from third-party websites available freely on the internet. This is simply to provide a link to stream, and all content is copyright of their owner.",
  "image": {
    "type": "cover",
    "url": "https://raw.githubusercontent.com/Bigblok-ai/allin1-stream/main/logo.png"
  },
  "groups": [
    {
      "id": "grp-tv-hoiquan",
      "name": "📺 Kênh Truyền Hình (10 LIVE)",
      "display": "vertical",
      "grid_number": 2,
      "enable_detail": false,
      "channels": [
        {
          "id": "tv-0",
          "name": "VTV1",
          "type": "single",
          "display": "thumbnail-only",
          "enable_detail": false,
          "labels": [
            {
              "text": "● LIVE",
              "position": "top-left",
              "color": "#00000080",
              "text_color": "#ff4444"
            }
          ],
          "sources": [
            {
              "id": "src-tv-0-0",
              "name": "Source 1 - fptplay53",
              "contents": [
                {
                  "id": "ct-tv-0-0",
                  "name": "VTV1",
                  "streams": [
                    {
                      "id": "st-tv-0-0",
                      "name": "KT",
                      "stream_links": [
                        {
                          "id": "lnk-tv-0-0",
                          "name": "Link 1",
                          "type": "hls",
                          "default": true,
                          "url": "https://live.fptplay53.net/live/media/vtv1/live247-hls-avc/vtv1-avc1_5600000=10000-mp4a_131600=20000.m3u8",
                          "request_headers": []
                        }
                      ]
                    }
                  ]
                }
              ]
            },
            {
              "id": "src-tv-0-1",
              "name": "Source 2 - dpdns",
              "contents": [
                {
                  "id": "ct-tv-0-1",
                  "name": "VTV1",
                  "streams": [
                    {
                      "id": "st-tv-0-1",
                      "name": "KT",
                      "stream_links": [
                        {
                          "id": "lnk-tv-0-1",
                          "name": "Link 2",
                          "type": "hls",
                          "default": false,
                          "url": "https://toiyeuvietnam.dpdns.org/TuyetDoiKhongKinhDoanh/vtv1-hd/KenhCoBan.m3u8",
                          "request_headers": []
                        }
                      ]
                    }
                  ]
                }
              ]
            }
          ],
          "org_metadata": {
            "is_live": true,
            "time": "",
            "team_a": "VTV1",
            "team_b": ""
          },
          "image": {
            "padding": 1,
            "background_color": "#ffffff",
            "display": "contain",
            "url": "https://toiyeuvietnam.dpdns.org/Logo/vtv1-hd/KenhCoBan.png",
            "width": 1600,
            "height": 1200
          }
        },
        {
          "id": "tv-1",
          "name": "VTV2",
          "type": "single",
          "display": "thumbnail-only",
          "enable_detail": false,
          "labels": [
            {
              "text": "● LIVE",
              "position": "top-left",
              "color": "#00000080",
              "text_color": "#ff4444"
            }
          ],
          "sources": [
            {
              "id": "src-tv-1-0",
              "name": "Source 1 - fptplay53",
              "contents": [
                {
                  "id": "ct-tv-1-0",
                  "name": "VTV2",
                  "streams": [
                    {
                      "id": "st-tv-1-0",
                      "name": "KT",
                      "stream_links": [
                        {
                          "id": "lnk-tv-1-0",
                          "name": "Link 1",
                          "type": "hls",
                          "default": true,
                          "url": "https://live.fptplay53.net/live/media/vtv2/live247-hls-avc/vtv2-avc1_5600000=10000-mp4a_131600=20000.m3u8",
                          "request_headers": []
                        }
                      ]
                    }
                  ]
                }
              ]
            },
            {
              "id": "src-tv-1-1",
              "name": "Source 2 - dpdns",
              "contents": [
                {
                  "id": "ct-tv-1-1",
                  "name": "VTV2",
                  "streams": [
                    {
                      "id": "st-tv-1-1",
                      "name": "KT",
                      "stream_links": [
                        {
                          "id": "lnk-tv-1-1",
                          "name": "Link 2",
                          "type": "hls",
                          "default": false,
                          "url": "https://toiyeuvietnam.dpdns.org/TuyetDoiKhongKinhDoanh/vtv2-hd/KenhCoBan.m3u8",
                          "request_headers": []
                        }
                      ]
                    }
                  ]
                }
              ]
            }
          ],
          "org_metadata": {
            "is_live": true,
            "time": "",
            "team_a": "VTV2",
            "team_b": ""
          },
          "image": {
            "padding": 1,
            "background_color": "#ffffff",
            "display": "contain",
            "url": "https://toiyeuvietnam.dpdns.org/Logo/vtv2-hd/KenhCoBan.png",
            "width": 1600,
            "height": 1200
          }
        },
        {
          "id": "tv-2",
          "name": "VTV3",
          "type": "single",
          "display": "thumbnail-only",
          "enable_detail": false,
          "labels": [
            {
              "text": "● LIVE",
              "position": "top-left",
              "color": "#00000080",
              "text_color": "#ff4444"
            }
          ],
          "sources": [
            {
              "id": "src-tv-2-0",
              "name": "Source 1 - fptplay53",
              "contents": [
                {
                  "id": "ct-tv-2-0",
                  "name": "VTV3",
                  "streams": [
                    {
                      "id": "st-tv-2-0",
                      "name": "KT",
                      "stream_links": [
                        {
                          "id": "lnk-tv-2-0",
                          "name": "Link 1",
                          "type": "hls",
                          "default": true,
                          "url": "https://live-a.fptplay53.net/live/media/vtv3/live247-hls-avc/vtv3-avc1_5600000=10000-mp4a_131600=20000.m3u8",
                          "request_headers": []
                        }
                      ]
                    }
                  ]
                }
              ]
            },
            {
              "id": "src-tv-2-1",
              "name": "Source 2 - dpdns",
              "contents": [
                {
                  "id": "ct-tv-2-1",
                  "name": "VTV3",
                  "streams": [
                    {
                      "id": "st-tv-2-1",
                      "name": "KT",
                      "stream_links": [
                        {
                          "id": "lnk-tv-2-1",
                          "name": "Link 2",
                          "type": "hls",
                          "default": false,
                          "url": "https://toiyeuvietnam.dpdns.org/TuyetDoiKhongKinhDoanh/vtv3-hd/KenhCoBan.m3u8",
                          "request_headers": []
                        }
                      ]
                    }
                  ]
                }
              ]
            }
          ],
          "org_metadata": {
            "is_live": true,
            "time": "",
            "team_a": "VTV3",
            "team_b": ""
          },
          "image": {
            "padding": 1,
            "background_color": "#ffffff",
            "display": "contain",
            "url": "https://toiyeuvietnam.dpdns.org/Logo/vtv3-hd/KenhCoBan.png",
            "width": 1600,
            "height": 1200
          }
        },
        {
          "id": "tv-3",
          "name": "VTV5",
          "type": "single",
          "display": "thumbnail-only",
          "enable_detail": false,
          "labels": [
            {
              "text": "● LIVE",
              "position": "top-left",
              "color": "#00000080",
              "text_color": "#ff4444"
            }
          ],
          "sources": [
            {
              "id": "src-tv-3-0",
              "name": "Source 1 - fptplay53",
              "contents": [
                {
                  "id": "ct-tv-3-0",
                  "name": "VTV5",
                  "streams": [
                    {
                      "id": "st-tv-3-0",
                      "name": "KT",
                      "stream_links": [
                        {
                          "id": "lnk-tv-3-0",
                          "name": "Link 1",
                          "type": "hls",
                          "default": true,
                          "url": "https://live.fptplay53.net/live/media/vtv5/live247-hls-avc/vtv5-avc1_5600000=10000-mp4a_131600=20000.m3u8",
                          "request_headers": []
                        }
                      ]
                    }
                  ]
                }
              ]
            },
            {
              "id": "src-tv-3-1",
              "name": "Source 2 - dpdns",
              "contents": [
                {
                  "id": "ct-tv-3-1",
                  "name": "VTV5",
                  "streams": [
                    {
                      "id": "st-tv-3-1",
                      "name": "KT",
                      "stream_links": [
                        {
                          "id": "lnk-tv-3-1",
                          "name": "Link 2",
                          "type": "hls",
                          "default": false,
                          "url": "https://toiyeuvietnam.dpdns.org/TuyetDoiKhongKinhDoanh/vtv5-hd/KenhCoBan.m3u8",
                          "request_headers": []
                        }
                      ]
                    }
                  ]
                }
              ]
            }
          ],
          "org_metadata": {
            "is_live": true,
            "time": "",
            "team_a": "VTV5",
            "team_b": ""
          },
          "image": {
            "padding": 1,
            "background_color": "#ffffff",
            "display": "contain",
            "url": "https://toiyeuvietnam.dpdns.org/Logo/vtv5-hd/KenhCoBan.png",
            "width": 1600,
            "height": 1200
          }
        },
        {
          "id": "tv-4",
          "name": "VTV5 Tây Nguyên",
          "type": "single",
          "display": "thumbnail-only",
          "enable_detail": false,
          "labels": [
            {
              "text": "● LIVE",
              "position": "top-left",
              "color": "#00000080",
              "text_color": "#ff4444"
            }
          ],
          "sources": [
            {
              "id": "src-tv-4-0",
              "name": "Source 1 - fptplay53",
              "contents": [
                {
                  "id": "ct-tv-4-0",
                  "name": "VTV5 Tây Nguyên",
                  "streams": [
                    {
                      "id": "st-tv-4-0",
                      "name": "KT",
                      "stream_links": [
                        {
                          "id": "lnk-tv-4-0",
                          "name": "Link 1",
                          "type": "hls",
                          "default": true,
                          "url": "https://live.fptplay53.net/fnxhd1/vtv5taynguyen_vhls.smil/chunklist_b5000000.m3u8",
                          "request_headers": []
                        }
                      ]
                    }
                  ]
                }
              ]
            }
          ],
          "org_metadata": {
            "is_live": true,
            "time": "",
            "team_a": "VTV5 Tây Nguyên",
            "team_b": ""
          },
          "image": {
            "padding": 1,
            "background_color": "#ffffff",
            "display": "contain",
            "url": "https://toiyeuvietnam.dpdns.org/Logo/vtv5-tay-nguyen/KenhCoBan.png",
            "width": 1600,
            "height": 1200
          }
        },
        {
          "id": "tv-5",
          "name": "VTV6",
          "type": "single",
          "display": "thumbnail-only",
          "enable_detail": false,
          "labels": [
            {
              "text": "● LIVE",
              "position": "top-left",
              "color": "#00000080",
              "text_color": "#ff4444"
            }
          ],
          "sources": [
            {
              "id": "src-tv-5-0",
              "name": "Source 1 - fptplay53",
              "contents": [
                {
                  "id": "ct-tv-5-0",
                  "name": "VTV6",
                  "streams": [
                    {
                      "id": "st-tv-5-0",
                      "name": "KT",
                      "stream_links": [
                        {
                          "id": "lnk-tv-5-0",
                          "name": "Link 1",
                          "type": "hls",
                          "default": true,
                          "url": "https://live-a.fptplay53.net/live/media/vtv6/live247-hls-avc/vtv6-avc1_5600000=10000-mp4a_131600=20000.m3u8",
                          "request_headers": []
                        }
                      ]
                    }
                  ]
                }
              ]
            },
            {
              "id": "src-tv-5-1",
              "name": "Source 2 - dpdns",
              "contents": [
                {
                  "id": "ct-tv-5-1",
                  "name": "VTV6",
                  "streams": [
                    {
                      "id": "st-tv-5-1",
                      "name": "KT",
                      "stream_links": [
                        {
                          "id": "lnk-tv-5-1",
                          "name": "Link 2",
                          "type": "hls",
                          "default": false,
                          "url": "https://toiyeuvietnam.dpdns.org/TuyetDoiKhongKinhDoanh/vtv6-hd/KenhCoBan.m3u8",
                          "request_headers": []
                        }
                      ]
                    }
                  ]
                }
              ]
            }
          ],
          "org_metadata": {
            "is_live": true,
            "time": "",
            "team_a": "VTV6",
            "team_b": ""
          },
          "image": {
            "padding": 1,
            "background_color": "#ffffff",
            "display": "contain",
            "url": "https://toiyeuvietnam.dpdns.org/Logo/vtv6-hd-2/KenhBoSung.png",
            "width": 1600,
            "height": 1200
          }
        },
        {
          "id": "tv-6",
          "name": "VTV7",
          "type": "single",
          "display": "thumbnail-only",
          "enable_detail": false,
          "labels": [
            {
              "text": "● LIVE",
              "position": "top-left",
              "color": "#00000080",
              "text_color": "#ff4444"
            }
          ],
          "sources": [
            {
              "id": "src-tv-6-0",
              "name": "Source 1 - dpdns",
              "contents": [
                {
                  "id": "ct-tv-6-0",
                  "name": "VTV7",
                  "streams": [
                    {
                      "id": "st-tv-6-0",
                      "name": "KT",
                      "stream_links": [
                        {
                          "id": "lnk-tv-6-0",
                          "name": "Link 1",
                          "type": "hls",
                          "default": true,
                          "url": "https://toiyeuvietnam.dpdns.org/Logo/vtv7-hd/KenhCoBan.png",
                          "request_headers": []
                        }
                      ]
                    }
                  ]
                }
              ]
            },
            {
              "id": "src-tv-6-1",
              "name": "Source 2 - fptplay53",
              "contents": [
                {
                  "id": "ct-tv-6-1",
                  "name": "VTV7",
                  "streams": [
                    {
                      "id": "st-tv-6-1",
                      "name": "KT",
                      "stream_links": [
                        {
                          "id": "lnk-tv-6-1",
                          "name": "Link 2",
                          "type": "hls",
                          "default": false,
                          "url": "https://live.fptplay53.net/live/media/vtv7/live247-hls-avc/vtv7-avc1_5600000=10000-mp4a_131600=20000.m3u8",
                          "request_headers": []
                        }
                      ]
                    }
                  ]
                }
              ]
            }
          ],
          "org_metadata": {
            "is_live": true,
            "time": "",
            "team_a": "VTV7",
            "team_b": ""
          },
          "image": {
            "padding": 1,
            "background_color": "#ffffff",
            "display": "contain",
            "url": "https://toiyeuvietnam.dpdns.org/Logo/vtv7-hd/KenhCoBan.png",
            "width": 1600,
            "height": 1200
          }
        },
        {
          "id": "tv-7",
          "name": "VTV9",
          "type": "single",
          "display": "thumbnail-only",
          "enable_detail": false,
          "labels": [
            {
              "text": "● LIVE",
              "position": "top-left",
              "color": "#00000080",
              "text_color": "#ff4444"
            }
          ],
          "sources": [
            {
              "id": "src-tv-7-0",
              "name": "Source 1 - fptplay53",
              "contents": [
                {
                  "id": "ct-tv-7-0",
                  "name": "VTV9",
                  "streams": [
                    {
                      "id": "st-tv-7-0",
                      "name": "KT",
                      "stream_links": [
                        {
                          "id": "lnk-tv-7-0",
                          "name": "Link 1",
                          "type": "hls",
                          "default": true,
                          "url": "https://live.fptplay53.net/live/media/vtv9/live247-hls-avc/vtv9-avc1_5600000=10000-mp4a_131600=20000.m3u8",
                          "request_headers": []
                        }
                      ]
                    }
                  ]
                }
              ]
            },
            {
              "id": "src-tv-7-1",
              "name": "Source 2 - dpdns",
              "contents": [
                {
                  "id": "ct-tv-7-1",
                  "name": "VTV9",
                  "streams": [
                    {
                      "id": "st-tv-7-1",
                      "name": "KT",
                      "stream_links": [
                        {
                          "id": "lnk-tv-7-1",
                          "name": "Link 2",
                          "type": "hls",
                          "default": false,
                          "url": "https://toiyeuvietnam.dpdns.org/TuyetDoiKhongKinhDoanh/vtv9-hd/KenhCoBan.m3u8",
                          "request_headers": []
                        }
                      ]
                    }
                  ]
                }
              ]
            }
          ],
          "org_metadata": {
            "is_live": true,
            "time": "",
            "team_a": "VTV9",
            "team_b": ""
          },
          "image": {
            "padding": 1,
            "background_color": "#ffffff",
            "display": "contain",
            "url": "https://toiyeuvietnam.dpdns.org/Logo/vtv9-hd/KenhCoBan.png",
            "width": 1600,
            "height": 1200
          }
        },
        {
          "id": "tv-8",
          "name": "VTV10",
          "type": "single",
          "display": "thumbnail-only",
          "enable_detail": false,
          "labels": [
            {
              "text": "● LIVE",
              "position": "top-left",
              "color": "#00000080",
              "text_color": "#ff4444"
            }
          ],
          "sources": [
            {
              "id": "src-tv-8-0",
              "name": "Source 1 - fptplay53",
              "contents": [
                {
                  "id": "ct-tv-8-0",
                  "name": "VTV10",
                  "streams": [
                    {
                      "id": "st-tv-8-0",
                      "name": "KT",
                      "stream_links": [
                        {
                          "id": "lnk-tv-8-0",
                          "name": "Link 1",
                          "type": "hls",
                          "default": true,
                          "url": "https://live.fptplay53.net/live/media/vtv10/live247-hls-avc/vtv10-avc1_5600000=10000-mp4a_131600=20000.m3u8",
                          "request_headers": []
                        }
                      ]
                    }
                  ]
                }
              ]
            }
          ],
          "org_metadata": {
            "is_live": true,
            "time": "",
            "team_a": "VTV10",
            "team_b": ""
          },
          "image": {
            "padding": 1,
            "background_color": "#ffffff",
            "display": "contain",
            "url": "https://toiyeuvietnam.dpdns.org/Logo/vtv10-hd/KenhCoBan.png",
            "width": 1600,
            "height": 1200
          }
        },
        {
          "id": "tv-9",
          "name": "HTV Thể Thao",
          "type": "single",
          "display": "thumbnail-only",
          "enable_detail": false,
          "labels": [
            {
              "text": "● LIVE",
              "position": "top-left",
              "color": "#00000080",
              "text_color": "#ff4444"
            }
          ],
          "sources": [
            {
              "id": "src-tv-9-0",
              "name": "Source 1 - fptplay53",
              "contents": [
                {
                  "id": "ct-tv-9-0",
                  "name": "HTV Thể Thao",
                  "streams": [
                    {
                      "id": "st-tv-9-0",
                      "name": "KT",
                      "stream_links": [
                        {
                          "id": "lnk-tv-9-0",
                          "name": "Link 1",
                          "type": "hls",
                          "default": true,
                          "url": "https://live.fptplay53.net/epzhd1/htvcthethao_vhls.smil/chunklist_b5000000.m3u8",
                          "request_headers": []
                        }
                      ]
                    }
                  ]
                }
              ]
            },
            {
              "id": "src-tv-9-1",
              "name": "Source 2 - duckdns",
              "contents": [
                {
                  "id": "ct-tv-9-1",
                  "name": "HTV Thể Thao",
                  "streams": [
                    {
                      "id": "st-tv-9-1",
                      "name": "KT",
                      "stream_links": [
                        {
                          "id": "lnk-tv-9-1",
                          "name": "Link 2",
                          "type": "hls",
                          "default": false,
                          "url": "https://sgclient.duckdns.org/source/vieon.m3u8?id=htvthethao",
                          "request_headers": []
                        }
                      ]
                    }
                  ]
                }
              ]
            }
          ],
          "org_metadata": {
            "is_live": true,
            "time": "",
            "team_a": "HTV Thể Thao",
            "team_b": ""
          },
          "image": {
            "padding": 1,
            "background_color": "#ffffff",
            "display": "contain",
            "url": "https://toiyeuvietnam.dpdns.org/Logo/htv-the-thao/KenhCoBan.png",
            "width": 1600,
            "height": 1200
          }
        }
      ]
    },
    {
      "id": "grp-bóng-đá",
      "name": "⚽ Bóng Đá (2 LIVE)",
      "display": "vertical",
      "grid_number": 2,
      "enable_detail": false,
      "channels": [
        {
          "id": "hqlive-f4d569d459",
          "name": "Germany vs Paraguay | 03:30 30/06",
          "type": "single",
          "display": "thumbnail-only",
          "enable_detail": false,
          "labels": [
            {
              "text": "● LIVE",
              "position": "top-left",
              "color": "#00000080",
              "text_color": "#ff4444"
            }
          ],
          "sources": [
            {
              "id": "src-f4d569d459",
              "name": "HoiQuanTV",
              "contents": [
                {
                  "id": "ct-f4d569d459",
                  "name": "Germany vs Paraguay",
                  "streams": [
                    {
                      "id": "st-f4d569d459",
                      "name": "HQ",
                      "stream_links": [
                        {
                          "id": "lnk-b10e5b640b",
                          "name": "BLV THẦN THÔNG",
                          "type": "hls",
                          "default": true,
                          "url": "https://tdlive.yarncdn.live/live/tdtv_blv_taovannghe/playlist.m3u8",
                          "request_headers": [
                            {
                              "key": "Referer",
                              "value": "https://sv2.hoiquan3.live/"
                            },
                            {
                              "key": "User-Agent",
                              "value": "Mozilla/5.0"
                            }
                          ]
                        },
                        {
                          "id": "lnk-b0c182498f",
                          "name": "BLV PHAN QUẨY",
                          "type": "hls",
                          "default": false,
                          "url": "https://hqlive.yarncdn.live/live/hqtv_blv_phanquay/playlist.m3u8",
                          "request_headers": [
                            {
                              "key": "Referer",
                              "value": "https://sv2.hoiquan3.live/"
                            },
                            {
                              "key": "User-Agent",
                              "value": "Mozilla/5.0"
                            }
                          ]
                        }
                      ]
                    }
                  ]
                }
              ]
            },
            {
              "id": "src-0197508d7f",
              "name": "XayConTV",
              "contents": [
                {
                  "id": "ct-0197508d7f",
                  "name": "Germany vs Paraguay",
                  "streams": [
                    {
                      "id": "st-0197508d7f",
                      "name": "Xaycon - BLV Bịp Con",
                      "stream_links": [
                        {
                          "id": "lnk-30319ba8f3",
                          "name": "Link FHD",
                          "type": "hls",
                          "default": true,
                          "url": "https://xclive.yarncdn.live/live/xctv_blv_bipcon/playlist.m3u8",
                          "request_headers": [
                            {
                              "key": "Referer",
                              "value": "https://sv2.xaycon3.live/"
                            },
                            {
                              "key": "Origin",
                              "value": "https://sv2.xaycon3.live"
                            },
                            {
                              "key": "User-Agent",
                              "value": "Mozilla/5.0"
                            }
                          ]
                        }
                      ]
                    }
                  ]
                }
              ]
            },
            {
              "id": "src-5d5a237908",
              "name": "XayConTV",
              "contents": [
                {
                  "id": "ct-5d5a237908",
                  "name": "Germany vs Paraguay",
                  "streams": [
                    {
                      "id": "st-5d5a237908",
                      "name": "Xaycon - BLV Chìm Sâu",
                      "stream_links": [
                        {
                          "id": "lnk-fa5c7698a5",
                          "name": "Link FHD",
                          "type": "hls",
                          "default": true,
                          "url": "https://xclive.yarncdn.live/live/xctv_blv_tholan/playlist.m3u8",
                          "request_headers": [
                            {
                              "key": "Referer",
                              "value": "https://sv2.xaycon3.live/"
                            },
                            {
                              "key": "Origin",
                              "value": "https://sv2.xaycon3.live"
                            },
                            {
                              "key": "User-Agent",
                              "value": "Mozilla/5.0"
                            }
                          ]
                        }
                      ]
                    }
                  ]
                }
              ]
            },
            {
              "id": "src-806a0eb2b7",
              "name": "XayConTV",
              "contents": [
                {
                  "id": "ct-806a0eb2b7",
                  "name": "Germany vs Paraguay",
                  "streams": [
                    {
                      "id": "st-806a0eb2b7",
                      "name": "Xaycon - BLV Tam Mao",
                      "stream_links": [
                        {
                          "id": "lnk-bccd486b79",
                          "name": "Link FHD",
                          "type": "hls",
                          "default": true,
                          "url": "https://xclive.yarncdn.live/live/xctv_blv_tammao/playlist.m3u8",
                          "request_headers": [
                            {
                              "key": "Referer",
                              "value": "https://sv2.xaycon3.live/"
                            },
                            {
                              "key": "Origin",
                              "value": "https://sv2.xaycon3.live"
                            },
                            {
                              "key": "User-Agent",
                              "value": "Mozilla/5.0"
                            }
                          ]
                        }
                      ]
                    }
                  ]
                }
              ]
            }
          ],
          "org_metadata": {
            "league": "World Cup",
            "team_a": "Germany",
            "team_b": "Paraguay",
            "logo_a": "https://upload.wikimedia.org/wikipedia/commons/thumb/b/ba/Flag_of_Germany.svg/1920px-Flag_of_Germany.svg.png",
            "logo_b": "https://upload.wikimedia.org/wikipedia/commons/thumb/2/27/Flag_of_Paraguay.svg/250px-Flag_of_Paraguay.svg.png",
            "time": "03:30 30/06",
            "blv": "BLV THẦN THÔNG, BLV PHAN QUẨY",
            "is_live": true,
            "sport_slug": "bong-da"
          },
          "image": {
            "padding": 1,
            "background_color": "#ffffff",
            "display": "contain",
            "url": "https://raw.githubusercontent.com/jasminliu98/hoiquan-stream/refs/heads/main/thumbs/Germany_Paraguay_03-30 30-06_5f0f1ba3_20260630.png?v=5f0f1ba3",
            "width": 1600,
            "height": 1200
          }
        },
        {
          "id": "bg-78719f11fa",
          "name": "Brazil vs Japan | 00:00 30/06",
          "type": "single",
          "display": "thumbnail-only",
          "enable_detail": false,
          "labels": [
            {
              "text": "● LIVE",
              "position": "top-left",
              "color": "#00000080",
              "text_color": "#ff4444"
            }
          ],
          "sources": [
            {
              "id": "src-78719f11fa",
              "name": "BugioTV",
              "contents": [
                {
                  "id": "ct-78719f11fa",
                  "name": "Brazil vs Japan",
                  "streams": [
                    {
                      "id": "st-78719f11fa",
                      "name": "BG",
                      "stream_links": [
                        {
                          "id": "lnk-51a73d71ba",
                          "name": "Link FHD",
                          "type": "hls",
                          "default": true,
                          "url": "https://bglive.yarncdn.live/live/bgtv_blv_mason/playlist.m3u8",
                          "request_headers": [
                            {
                              "key": "Referer",
                              "value": "https://sv1.bugio9.live/"
                            },
                            {
                              "key": "User-Agent",
                              "value": "Mozilla/5.0"
                            }
                          ]
                        }
                      ]
                    }
                  ]
                }
              ]
            }
          ],
          "org_metadata": {
            "league": "World Cup",
            "team_a": "Brazil",
            "team_b": "Japan",
            "logo_a": "https://media.api-sports.io/football/teams/6.png",
            "logo_b": "https://media.api-sports.io/football/teams/12.png",
            "start_time": "2026-06-30T00:00:00",
            "blv": "BLV Mao Từn",
            "is_live": true,
            "cate_type": "football"
          },
          "image": {
            "padding": 1,
            "background_color": "#ffffff",
            "display": "contain",
            "url": "https://raw.githubusercontent.com/jasminliu98/bugio-stream/refs/heads/main/thumbs/bg-78719f11fa_20f5dece_20260630.png?v=20f5dece",
            "width": 1600,
            "height": 1200
          }
        },
        {
          "id": "hqlive-a375849fc1",
          "name": "Netherlands vs Morocco | 08:00 30/06",
          "type": "single",
          "display": "thumbnail-only",
          "enable_detail": false,
          "labels": [
            {
              "text": "🕐 Sắp",
              "position": "top-left",
              "color": "#00000080",
              "text_color": "#aaaaaa"
            }
          ],
          "sources": [
            {
              "id": "src-a375849fc1",
              "name": "HoiQuanTV",
              "contents": [
                {
                  "id": "ct-a375849fc1",
                  "name": "Netherlands vs Morocco",
                  "streams": [
                    {
                      "id": "st-a375849fc1",
                      "name": "HQ",
                      "stream_links": []
                    }
                  ]
                }
              ]
            },
            {
              "id": "src-cf4281b764",
              "name": "QuechoaTV",
              "contents": [
                {
                  "id": "ct-cf4281b764",
                  "name": "Netherlands vs Morocco",
                  "streams": [
                    {
                      "id": "st-cf4281b764",
                      "name": "Quechoa - DƯA HẤU, VỎ QUÝT, NEM CHUA",
                      "stream_links": [
                        {
                          "id": "lnk-0e88644c2d",
                          "name": "Link FHD",
                          "type": "hls",
                          "default": true,
                          "url": "https://ahghndtkyqmm-pull.bpmedialive.com/quechoa/blv_duahau.m3u8",
                          "request_headers": [
                            {
                              "key": "Referer",
                              "value": "https://quechoa10.live/"
                            },
                            {
                              "key": "Origin",
                              "value": "https://quechoa10.live"
                            },
                            {
                              "key": "User-Agent",
                              "value": "Mozilla/5.0"
                            }
                          ]
                        }
                      ]
                    }
                  ]
                }
              ]
            },
            {
              "id": "src-817ef384d7",
              "name": "XayConTV",
              "contents": [
                {
                  "id": "ct-817ef384d7",
                  "name": "Netherlands vs Morocco",
                  "streams": [
                    {
                      "id": "st-817ef384d7",
                      "name": "Xaycon - BLV Rồng Đất",
                      "stream_links": [
                        {
                          "id": "lnk-221ed1ffcc",
                          "name": "Link FHD",
                          "type": "hls",
                          "default": true,
                          "url": "https://xclive.yarncdn.live/live/xctv_blv_rongdat/playlist.m3u8",
                          "request_headers": [
                            {
                              "key": "Referer",
                              "value": "https://sv2.xaycon3.live/"
                            },
                            {
                              "key": "Origin",
                              "value": "https://sv2.xaycon3.live"
                            },
                            {
                              "key": "User-Agent",
                              "value": "Mozilla/5.0"
                            }
                          ]
                        }
                      ]
                    }
                  ]
                }
              ]
            },
            {
              "id": "src-537a479158",
              "name": "XayConTV",
              "contents": [
                {
                  "id": "ct-537a479158",
                  "name": "Netherlands vs Morocco",
                  "streams": [
                    {
                      "id": "st-537a479158",
                      "name": "Xaycon - BLV Chuối",
                      "stream_links": [
                        {
                          "id": "lnk-fde7f94b4e",
                          "name": "Link FHD",
                          "type": "hls",
                          "default": true,
                          "url": "https://xclive.yarncdn.live/live/xctv_blv_chuoi/playlist.m3u8",
                          "request_headers": [
                            {
                              "key": "Referer",
                              "value": "https://sv2.xaycon3.live/"
                            },
                            {
                              "key": "Origin",
                              "value": "https://sv2.xaycon3.live"
                            },
                            {
                              "key": "User-Agent",
                              "value": "Mozilla/5.0"
                            }
                          ]
                        }
                      ]
                    }
                  ]
                }
              ]
            },
            {
              "id": "src-82debd8a12",
              "name": "BugioTV",
              "contents": [
                {
                  "id": "ct-82debd8a12",
                  "name": "Netherlands vs Morocco",
                  "streams": [
                    {
                      "id": "st-82debd8a12",
                      "name": "Bugio - BLV Max",
                      "stream_links": [
                        {
                          "id": "lnk-ad68922ab2",
                          "name": "Link FHD",
                          "type": "hls",
                          "default": true,
                          "url": "https://bglive.yarncdn.live/live/bgtv_blv_max/playlist.m3u8",
                          "request_headers": [
                            {
                              "key": "Referer",
                              "value": "https://sv1.bugio9.live/"
                            },
                            {
                              "key": "User-Agent",
                              "value": "Mozilla/5.0"
                            }
                          ]
                        }
                      ]
                    }
                  ]
                }
              ]
            },
            {
              "id": "src-3a246af267",
              "name": "BugioTV",
              "contents": [
                {
                  "id": "ct-3a246af267",
                  "name": "Netherlands vs Morocco",
                  "streams": [
                    {
                      "id": "st-3a246af267",
                      "name": "Bugio - BLV Tiểu Trà Đá",
                      "stream_links": [
                        {
                          "id": "lnk-0ba3f9d037",
                          "name": "Link FHD",
                          "type": "hls",
                          "default": true,
                          "url": "https://bglive.yarncdn.live/live/bgtv_blv_trada/playlist.m3u8",
                          "request_headers": [
                            {
                              "key": "Referer",
                              "value": "https://sv1.bugio9.live/"
                            },
                            {
                              "key": "User-Agent",
                              "value": "Mozilla/5.0"
                            }
                          ]
                        }
                      ]
                    }
                  ]
                }
              ]
            }
          ],
          "org_metadata": {
            "league": "World Cup",
            "team_a": "Netherlands",
            "team_b": "Morocco",
            "logo_a": "https://media.api-sports.io/football/teams/1118.png",
            "logo_b": "https://upload.wikimedia.org/wikipedia/commons/thumb/2/2c/Flag_of_Morocco.svg/1280px-Flag_of_Morocco.svg.png",
            "time": "08:00 30/06",
            "blv": "BLV THẦN THÔNG",
            "is_live": false,
            "sport_slug": "bong-da"
          },
          "image": {
            "padding": 1,
            "background_color": "#ffffff",
            "display": "contain",
            "url": "https://raw.githubusercontent.com/jasminliu98/hoiquan-stream/refs/heads/main/thumbs/Netherlands_Morocco_08-00 30-06_a20fb9ff_20260630.png?v=a20fb9ff",
            "width": 1600,
            "height": 1200
          }
        },
        {
          "id": "hqlive-e35d40aa03",
          "name": "Logan Lightning vs Redlands United | 17:30 30/06",
          "type": "single",
          "display": "thumbnail-only",
          "enable_detail": false,
          "labels": [
            {
              "text": "🕐 Sắp",
              "position": "top-left",
              "color": "#00000080",
              "text_color": "#aaaaaa"
            }
          ],
          "sources": [
            {
              "id": "src-e35d40aa03",
              "name": "HoiQuanTV",
              "contents": [
                {
                  "id": "ct-e35d40aa03",
                  "name": "Logan Lightning vs Redlands United",
                  "streams": [
                    {
                      "id": "st-e35d40aa03",
                      "name": "HQ",
                      "stream_links": []
                    }
                  ]
                }
              ]
            },
            {
              "id": "src-d2d50ecad5",
              "name": "XayConTV",
              "contents": [
                {
                  "id": "ct-d2d50ecad5",
                  "name": "Logan Lightning vs Redlands United",
                  "streams": [
                    {
                      "id": "st-d2d50ecad5",
                      "name": "Xaycon - BLV Tam Mao",
                      "stream_links": [
                        {
                          "id": "lnk-bccd486b79",
                          "name": "Link FHD",
                          "type": "hls",
                          "default": true,
                          "url": "https://xclive.yarncdn.live/live/xctv_blv_tammao/playlist.m3u8",
                          "request_headers": [
                            {
                              "key": "Referer",
                              "value": "https://sv2.xaycon3.live/"
                            },
                            {
                              "key": "Origin",
                              "value": "https://sv2.xaycon3.live"
                            },
                            {
                              "key": "User-Agent",
                              "value": "Mozilla/5.0"
                            }
                          ]
                        }
                      ]
                    }
                  ]
                }
              ]
            }
          ],
          "org_metadata": {
            "league": "Queensland Premier League",
            "team_a": "Logan Lightning",
            "team_b": "Redlands United",
            "logo_a": "https://media.api-sports.io/football/teams/11180.png",
            "logo_b": "https://media.api-sports.io/football/teams/10222.png",
            "time": "17:30 30/06",
            "blv": "BLV PHAN CA",
            "is_live": false,
            "sport_slug": "bong-da"
          },
          "image": {
            "padding": 1,
            "background_color": "#ffffff",
            "display": "contain",
            "url": "https://raw.githubusercontent.com/jasminliu98/hoiquan-stream/refs/heads/main/thumbs/Logan Lightning_Redlands United_17-30 30-06_921a2950_20260630.png?v=921a2950",
            "width": 1600,
            "height": 1200
          }
        },
        {
          "id": "hqlive-321006eaad",
          "name": "VPS vs Inter Turku | 22:00 30/06",
          "type": "single",
          "display": "thumbnail-only",
          "enable_detail": false,
          "labels": [
            {
              "text": "🕐 Sắp",
              "position": "top-left",
              "color": "#00000080",
              "text_color": "#aaaaaa"
            }
          ],
          "sources": [
            {
              "id": "src-321006eaad",
              "name": "HoiQuanTV",
              "contents": [
                {
                  "id": "ct-321006eaad",
                  "name": "VPS vs Inter Turku",
                  "streams": [
                    {
                      "id": "st-321006eaad",
                      "name": "HQ",
                      "stream_links": []
                    }
                  ]
                }
              ]
            }
          ],
          "org_metadata": {
            "league": "Suomen Cup",
            "team_a": "VPS",
            "team_b": "Inter Turku",
            "logo_a": "https://media.api-sports.io/football/teams/650.png",
            "logo_b": "https://media.api-sports.io/football/teams/1164.png",
            "time": "22:00 30/06",
            "blv": "BLV TÁO GIÀ",
            "is_live": false,
            "sport_slug": "bong-da"
          },
          "image": {
            "padding": 1,
            "background_color": "#ffffff",
            "display": "contain",
            "url": "https://raw.githubusercontent.com/jasminliu98/hoiquan-stream/refs/heads/main/thumbs/VPS_Inter Turku_22-00 30-06_8569433f_20260630.png?v=8569433f",
            "width": 1600,
            "height": 1200
          }
        },
        {
          "id": "hqlive-8f66a5103d",
          "name": "FK Liepaja vs Ogre United | 23:00 30/06",
          "type": "single",
          "display": "thumbnail-only",
          "enable_detail": false,
          "labels": [
            {
              "text": "🕐 Sắp",
              "position": "top-left",
              "color": "#00000080",
              "text_color": "#aaaaaa"
            }
          ],
          "sources": [
            {
              "id": "src-8f66a5103d",
              "name": "HoiQuanTV",
              "contents": [
                {
                  "id": "ct-8f66a5103d",
                  "name": "FK Liepaja vs Ogre United",
                  "streams": [
                    {
                      "id": "st-8f66a5103d",
                      "name": "HQ",
                      "stream_links": []
                    }
                  ]
                }
              ]
            },
            {
              "id": "src-28e9e8449b",
              "name": "XayConTV",
              "contents": [
                {
                  "id": "ct-28e9e8449b",
                  "name": "FK Liepaja vs Ogre United",
                  "streams": [
                    {
                      "id": "st-28e9e8449b",
                      "name": "Xaycon - BLV Bịp Con",
                      "stream_links": [
                        {
                          "id": "lnk-30319ba8f3",
                          "name": "Link FHD",
                          "type": "hls",
                          "default": true,
                          "url": "https://xclive.yarncdn.live/live/xctv_blv_bipcon/playlist.m3u8",
                          "request_headers": [
                            {
                              "key": "Referer",
                              "value": "https://sv2.xaycon3.live/"
                            },
                            {
                              "key": "Origin",
                              "value": "https://sv2.xaycon3.live"
                            },
                            {
                              "key": "User-Agent",
                              "value": "Mozilla/5.0"
                            }
                          ]
                        }
                      ]
                    }
                  ]
                }
              ]
            }
          ],
          "org_metadata": {
            "league": "Virsliga",
            "team_a": "FK Liepaja",
            "team_b": "Ogre United",
            "logo_a": "https://media.api-sports.io/football/teams/661.png",
            "logo_b": "https://media.api-sports.io/football/teams/18936.png",
            "time": "23:00 30/06",
            "blv": "BLV PHAN CA",
            "is_live": false,
            "sport_slug": "bong-da"
          },
          "image": {
            "padding": 1,
            "background_color": "#ffffff",
            "display": "contain",
            "url": "https://raw.githubusercontent.com/jasminliu98/hoiquan-stream/refs/heads/main/thumbs/FK Liepaja_Ogre United_23-00 30-06_6e66dd2c_20260630.png?v=6e66dd2c",
            "width": 1600,
            "height": 1200
          }
        },
        {
          "id": "qc-2b32a6f33c",
          "name": "Ivory Coast vs Norway | 00:00 01/07",
          "type": "single",
          "display": "thumbnail-only",
          "enable_detail": false,
          "labels": [
            {
              "text": "🕐 Sắp",
              "position": "top-left",
              "color": "#00000080",
              "text_color": "#aaaaaa"
            }
          ],
          "sources": [
            {
              "id": "src-2b32a6f33c",
              "name": "QuechoaTV",
              "contents": [
                {
                  "id": "ct-2b32a6f33c",
                  "name": "Ivory Coast vs Norway",
                  "streams": [
                    {
                      "id": "st-2b32a6f33c",
                      "name": "QC",
                      "stream_links": [
                        {
                          "id": "lnk-67419b1cbc",
                          "name": "Link FHD",
                          "type": "hls",
                          "default": true,
                          "url": "https://ahghndtkyqmm-pull.bpmedialive.com/quechoa/blv_khoaitay.m3u8",
                          "request_headers": [
                            {
                              "key": "Referer",
                              "value": "https://quechoa10.live/"
                            },
                            {
                              "key": "Origin",
                              "value": "https://quechoa10.live"
                            },
                            {
                              "key": "User-Agent",
                              "value": "Mozilla/5.0"
                            }
                          ]
                        }
                      ]
                    }
                  ]
                }
              ]
            },
            {
              "id": "src-47a66f1a2d",
              "name": "XayConTV",
              "contents": [
                {
                  "id": "ct-47a66f1a2d",
                  "name": "Ivory Coast vs Norway",
                  "streams": [
                    {
                      "id": "st-47a66f1a2d",
                      "name": "Xaycon - BLV Bịp Con",
                      "stream_links": [
                        {
                          "id": "lnk-30319ba8f3",
                          "name": "Link FHD",
                          "type": "hls",
                          "default": true,
                          "url": "https://xclive.yarncdn.live/live/xctv_blv_bipcon/playlist.m3u8",
                          "request_headers": [
                            {
                              "key": "Referer",
                              "value": "https://sv2.xaycon3.live/"
                            },
                            {
                              "key": "Origin",
                              "value": "https://sv2.xaycon3.live"
                            },
                            {
                              "key": "User-Agent",
                              "value": "Mozilla/5.0"
                            }
                          ]
                        }
                      ]
                    }
                  ]
                }
              ]
            },
            {
              "id": "src-43e1e0cdf5",
              "name": "XayConTV",
              "contents": [
                {
                  "id": "ct-43e1e0cdf5",
                  "name": "Ivory Coast vs Norway",
                  "streams": [
                    {
                      "id": "st-43e1e0cdf5",
                      "name": "Xaycon - BLV Chìm Sâu",
                      "stream_links": [
                        {
                          "id": "lnk-fa5c7698a5",
                          "name": "Link FHD",
                          "type": "hls",
                          "default": true,
                          "url": "https://xclive.yarncdn.live/live/xctv_blv_tholan/playlist.m3u8",
                          "request_headers": [
                            {
                              "key": "Referer",
                              "value": "https://sv2.xaycon3.live/"
                            },
                            {
                              "key": "Origin",
                              "value": "https://sv2.xaycon3.live"
                            },
                            {
                              "key": "User-Agent",
                              "value": "Mozilla/5.0"
                            }
                          ]
                        }
                      ]
                    }
                  ]
                }
              ]
            },
            {
              "id": "src-2a66e7278b",
              "name": "XayConTV",
              "contents": [
                {
                  "id": "ct-2a66e7278b",
                  "name": "Ivory Coast vs Norway",
                  "streams": [
                    {
                      "id": "st-2a66e7278b",
                      "name": "Xaycon - BLV Rồng Đất",
                      "stream_links": [
                        {
                          "id": "lnk-221ed1ffcc",
                          "name": "Link FHD",
                          "type": "hls",
                          "default": true,
                          "url": "https://xclive.yarncdn.live/live/xctv_blv_rongdat/playlist.m3u8",
                          "request_headers": [
                            {
                              "key": "Referer",
                              "value": "https://sv2.xaycon3.live/"
                            },
                            {
                              "key": "Origin",
                              "value": "https://sv2.xaycon3.live"
                            },
                            {
                              "key": "User-Agent",
                              "value": "Mozilla/5.0"
                            }
                          ]
                        }
                      ]
                    }
                  ]
                }
              ]
            }
          ],
          "org_metadata": {
            "league": "World Cup",
            "team_a": "Ivory Coast",
            "team_b": "Norway",
            "logo_a": "https://media.api-sports.io/football/teams/1501.png",
            "logo_b": "https://media.api-sports.io/football/teams/1090.png",
            "time": "00:00",
            "date": "01/07",
            "blv": "VỎ QUÝT, CHÈ XANH, NEM CHUA",
            "is_live": false,
            "sport_slug": "bong-da"
          },
          "image": {
            "padding": 1,
            "background_color": "#ffffff",
            "display": "contain",
            "url": "https://raw.githubusercontent.com/jasminliu98/quechoa-stream/refs/heads/main/thumbs/qc-2b32a6f33c_33ed78ec_20260630.png?v=33ed78ec",
            "width": 1600,
            "height": 1200
          }
        },
        {
          "id": "qc-d3c909b719",
          "name": "Belgium vs Senegal | 03:00 02/07",
          "type": "single",
          "display": "thumbnail-only",
          "enable_detail": false,
          "labels": [
            {
              "text": "🕐 Sắp",
              "position": "top-left",
              "color": "#00000080",
              "text_color": "#aaaaaa"
            }
          ],
          "sources": [
            {
              "id": "src-d3c909b719",
              "name": "QuechoaTV",
              "contents": [
                {
                  "id": "ct-d3c909b719",
                  "name": "Belgium vs Senegal",
                  "streams": [
                    {
                      "id": "st-d3c909b719",
                      "name": "QC",
                      "stream_links": [
                        {
                          "id": "lnk-6cafe33b0c",
                          "name": "Link FHD",
                          "type": "hls",
                          "default": true,
                          "url": "https://ahghndtkyqmm-pull.bpmedialive.com/quechoa/blv1.m3u8",
                          "request_headers": [
                            {
                              "key": "Referer",
                              "value": "https://quechoa10.live/"
                            },
                            {
                              "key": "Origin",
                              "value": "https://quechoa10.live"
                            },
                            {
                              "key": "User-Agent",
                              "value": "Mozilla/5.0"
                            }
                          ]
                        }
                      ]
                    }
                  ]
                }
              ]
            }
          ],
          "org_metadata": {
            "league": "World Cup",
            "team_a": "Belgium",
            "team_b": "Senegal",
            "logo_a": "https://media.api-sports.io/football/teams/1.png",
            "logo_b": "https://media.api-sports.io/football/teams/13.png",
            "time": "03:00",
            "date": "02/07",
            "blv": "PUMA, VỎ QUÝT, NEM CHUA",
            "is_live": false,
            "sport_slug": "bong-da"
          },
          "image": {
            "padding": 1,
            "background_color": "#ffffff",
            "display": "contain",
            "url": "https://raw.githubusercontent.com/jasminliu98/quechoa-stream/refs/heads/main/thumbs/qc-d3c909b719_7a8f4b6a_20260630.png?v=7a8f4b6a",
            "width": 1600,
            "height": 1200
          }
        },
        {
          "id": "qc-3576abe966",
          "name": "France vs Sweden | 04:00 01/07",
          "type": "single",
          "display": "thumbnail-only",
          "enable_detail": false,
          "labels": [
            {
              "text": "🕐 Sắp",
              "position": "top-left",
              "color": "#00000080",
              "text_color": "#aaaaaa"
            }
          ],
          "sources": [
            {
              "id": "src-3576abe966",
              "name": "QuechoaTV",
              "contents": [
                {
                  "id": "ct-3576abe966",
                  "name": "France vs Sweden",
                  "streams": [
                    {
                      "id": "st-3576abe966",
                      "name": "QC",
                      "stream_links": [
                        {
                          "id": "lnk-6cafe33b0c",
                          "name": "Link FHD",
                          "type": "hls",
                          "default": true,
                          "url": "https://ahghndtkyqmm-pull.bpmedialive.com/quechoa/blv1.m3u8",
                          "request_headers": [
                            {
                              "key": "Referer",
                              "value": "https://quechoa10.live/"
                            },
                            {
                              "key": "Origin",
                              "value": "https://quechoa10.live"
                            },
                            {
                              "key": "User-Agent",
                              "value": "Mozilla/5.0"
                            }
                          ]
                        }
                      ]
                    }
                  ]
                }
              ]
            },
            {
              "id": "src-ae68be0155",
              "name": "XayConTV",
              "contents": [
                {
                  "id": "ct-ae68be0155",
                  "name": "France vs Sweden",
                  "streams": [
                    {
                      "id": "st-ae68be0155",
                      "name": "Xaycon - BLV Rồng Đất",
                      "stream_links": [
                        {
                          "id": "lnk-221ed1ffcc",
                          "name": "Link FHD",
                          "type": "hls",
                          "default": true,
                          "url": "https://xclive.yarncdn.live/live/xctv_blv_rongdat/playlist.m3u8",
                          "request_headers": [
                            {
                              "key": "Referer",
                              "value": "https://sv2.xaycon3.live/"
                            },
                            {
                              "key": "Origin",
                              "value": "https://sv2.xaycon3.live"
                            },
                            {
                              "key": "User-Agent",
                              "value": "Mozilla/5.0"
                            }
                          ]
                        }
                      ]
                    }
                  ]
                }
              ]
            },
            {
              "id": "src-68297bb334",
              "name": "XayConTV",
              "contents": [
                {
                  "id": "ct-68297bb334",
                  "name": "France vs Sweden",
                  "streams": [
                    {
                      "id": "st-68297bb334",
                      "name": "Xaycon - BLV Chìm Sâu",
                      "stream_links": [
                        {
                          "id": "lnk-fa5c7698a5",
                          "name": "Link FHD",
                          "type": "hls",
                          "default": true,
                          "url": "https://xclive.yarncdn.live/live/xctv_blv_tholan/playlist.m3u8",
                          "request_headers": [
                            {
                              "key": "Referer",
                              "value": "https://sv2.xaycon3.live/"
                            },
                            {
                              "key": "Origin",
                              "value": "https://sv2.xaycon3.live"
                            },
                            {
                              "key": "User-Agent",
                              "value": "Mozilla/5.0"
                            }
                          ]
                        }
                      ]
                    }
                  ]
                }
              ]
            },
            {
              "id": "src-a13bfc2b80",
              "name": "XayConTV",
              "contents": [
                {
                  "id": "ct-a13bfc2b80",
                  "name": "France vs Sweden",
                  "streams": [
                    {
                      "id": "st-a13bfc2b80",
                      "name": "Xaycon - BLV Bịp Con",
                      "stream_links": [
                        {
                          "id": "lnk-30319ba8f3",
                          "name": "Link FHD",
                          "type": "hls",
                          "default": true,
                          "url": "https://xclive.yarncdn.live/live/xctv_blv_bipcon/playlist.m3u8",
                          "request_headers": [
                            {
                              "key": "Referer",
                              "value": "https://sv2.xaycon3.live/"
                            },
                            {
                              "key": "Origin",
                              "value": "https://sv2.xaycon3.live"
                            },
                            {
                              "key": "User-Agent",
                              "value": "Mozilla/5.0"
                            }
                          ]
                        }
                      ]
                    }
                  ]
                }
              ]
            }
          ],
          "org_metadata": {
            "league": "World Cup",
            "team_a": "France",
            "team_b": "Sweden",
            "logo_a": "https://media.api-sports.io/football/teams/2.png",
            "logo_b": "https://media.api-sports.io/football/teams/5.png",
            "time": "04:00",
            "date": "01/07",
            "blv": "PUMA, VỎ QUÝT, NEM CHUA",
            "is_live": false,
            "sport_slug": "bong-da"
          },
          "image": {
            "padding": 1,
            "background_color": "#ffffff",
            "display": "contain",
            "url": "https://raw.githubusercontent.com/jasminliu98/quechoa-stream/refs/heads/main/thumbs/qc-3576abe966_6f968b3c_20260630.png?v=6f968b3c",
            "width": 1600,
            "height": 1200
          }
        },
        {
          "id": "qc-ba12d57272",
          "name": "Mexico vs Ecuador | 08:00 01/07",
          "type": "single",
          "display": "thumbnail-only",
          "enable_detail": false,
          "labels": [
            {
              "text": "🕐 Sắp",
              "position": "top-left",
              "color": "#00000080",
              "text_color": "#aaaaaa"
            }
          ],
          "sources": [
            {
              "id": "src-ba12d57272",
              "name": "QuechoaTV",
              "contents": [
                {
                  "id": "ct-ba12d57272",
                  "name": "Mexico vs Ecuador",
                  "streams": [
                    {
                      "id": "st-ba12d57272",
                      "name": "QC",
                      "stream_links": [
                        {
                          "id": "lnk-0e88644c2d",
                          "name": "Link FHD",
                          "type": "hls",
                          "default": true,
                          "url": "https://ahghndtkyqmm-pull.bpmedialive.com/quechoa/blv_duahau.m3u8",
                          "request_headers": [
                            {
                              "key": "Referer",
                              "value": "https://quechoa10.live/"
                            },
                            {
                              "key": "Origin",
                              "value": "https://quechoa10.live"
                            },
                            {
                              "key": "User-Agent",
                              "value": "Mozilla/5.0"
                            }
                          ]
                        }
                      ]
                    }
                  ]
                }
              ]
            },
            {
              "id": "src-5b4c4891cc",
              "name": "XayConTV",
              "contents": [
                {
                  "id": "ct-5b4c4891cc",
                  "name": "Mexico vs Ecuador",
                  "streams": [
                    {
                      "id": "st-5b4c4891cc",
                      "name": "Xaycon - BLV Chìm Sâu",
                      "stream_links": [
                        {
                          "id": "lnk-fa5c7698a5",
                          "name": "Link FHD",
                          "type": "hls",
                          "default": true,
                          "url": "https://xclive.yarncdn.live/live/xctv_blv_tholan/playlist.m3u8",
                          "request_headers": [
                            {
                              "key": "Referer",
                              "value": "https://sv2.xaycon3.live/"
                            },
                            {
                              "key": "Origin",
                              "value": "https://sv2.xaycon3.live"
                            },
                            {
                              "key": "User-Agent",
                              "value": "Mozilla/5.0"
                            }
                          ]
                        }
                      ]
                    }
                  ]
                }
              ]
            },
            {
              "id": "src-b23a30a184",
              "name": "XayConTV",
              "contents": [
                {
                  "id": "ct-b23a30a184",
                  "name": "Mexico vs Ecuador",
                  "streams": [
                    {
                      "id": "st-b23a30a184",
                      "name": "Xaycon - BLV Tam Mao",
                      "stream_links": [
                        {
                          "id": "lnk-bccd486b79",
                          "name": "Link FHD",
                          "type": "hls",
                          "default": true,
                          "url": "https://xclive.yarncdn.live/live/xctv_blv_tammao/playlist.m3u8",
                          "request_headers": [
                            {
                              "key": "Referer",
                              "value": "https://sv2.xaycon3.live/"
                            },
                            {
                              "key": "Origin",
                              "value": "https://sv2.xaycon3.live"
                            },
                            {
                              "key": "User-Agent",
                              "value": "Mozilla/5.0"
                            }
                          ]
                        }
                      ]
                    }
                  ]
                }
              ]
            }
          ],
          "org_metadata": {
            "league": "World Cup",
            "team_a": "Mexico",
            "team_b": "Ecuador",
            "logo_a": "https://media.api-sports.io/football/teams/16.png",
            "logo_b": "https://media.api-sports.io/football/teams/2382.png",
            "time": "08:00",
            "date": "01/07",
            "blv": "DƯA HẤU, CHÈ XANH, VĂN MINH",
            "is_live": false,
            "sport_slug": "bong-da"
          },
          "image": {
            "padding": 1,
            "background_color": "#ffffff",
            "display": "contain",
            "url": "https://raw.githubusercontent.com/jasminliu98/quechoa-stream/refs/heads/main/thumbs/qc-ba12d57272_aa82e7b3_20260630.png?v=aa82e7b3",
            "width": 1600,
            "height": 1200
          }
        },
        {
          "id": "xc-a99553823d",
          "name": "Ha Noi 2 W vs Ho Chi Minh City 2 W | 16:00 30/06",
          "type": "single",
          "display": "thumbnail-only",
          "enable_detail": false,
          "labels": [
            {
              "text": "🕐 Sắp",
              "position": "top-left",
              "color": "#00000080",
              "text_color": "#aaaaaa"
            }
          ],
          "sources": [
            {
              "id": "src-a99553823d",
              "name": "XayConTV",
              "contents": [
                {
                  "id": "ct-a99553823d",
                  "name": "Ha Noi 2 W vs Ho Chi Minh City 2 W",
                  "streams": [
                    {
                      "id": "st-a99553823d",
                      "name": "XC",
                      "stream_links": [
                        {
                          "id": "lnk-fde7f94b4e",
                          "name": "Link FHD",
                          "type": "hls",
                          "default": true,
                          "url": "https://xclive.yarncdn.live/live/xctv_blv_chuoi/playlist.m3u8",
                          "request_headers": [
                            {
                              "key": "Referer",
                              "value": "https://sv2.xaycon3.live/"
                            },
                            {
                              "key": "Origin",
                              "value": "https://sv2.xaycon3.live"
                            },
                            {
                              "key": "User-Agent",
                              "value": "Mozilla/5.0"
                            }
                          ]
                        }
                      ]
                    }
                  ]
                }
              ]
            }
          ],
          "org_metadata": {
            "league": "Vietnam Wonmen League",
            "team_a": "Ha Noi",
            "team_b": "Ho Chi Minh",
            "logo_a": "https://upload.wikimedia.org/wikipedia/vi/b/b4/Logo_H%C3%A0_N%E1%BB%99i_FC.png",
            "logo_b": "https://upload.wikimedia.org/wikipedia/vi/thumb/4/47/Logo_of_Cong_An_Ho_Chi_Minh_City_football_club%2C_from_Ho_Chi_Minh_City%2C_from_2025.svg/250px-Logo_of_Cong_An_Ho_Chi_Minh_City_football_club%2C_from_Ho_Chi_Minh_City%2C_from_2025.svg.png",
            "time": "16:00",
            "date": "30/06",
            "blv": "BLV Chuối",
            "is_live": false,
            "sport_slug": "bong-da"
          },
          "image": {
            "padding": 1,
            "background_color": "#ffffff",
            "display": "contain",
            "url": "https://raw.githubusercontent.com/jasminliu98/xaycon-stream/refs/heads/main/thumbs/xc-a99553823d_99d7c364_20260630.png?v=99d7c364",
            "width": 1600,
            "height": 1200
          }
        },
        {
          "id": "qc-7858570ddf",
          "name": "England vs Congo DR | 23:00 01/07",
          "type": "single",
          "display": "thumbnail-only",
          "enable_detail": false,
          "labels": [
            {
              "text": "🕐 Sắp",
              "position": "top-left",
              "color": "#00000080",
              "text_color": "#aaaaaa"
            }
          ],
          "sources": [
            {
              "id": "src-7858570ddf",
              "name": "QuechoaTV",
              "contents": [
                {
                  "id": "ct-7858570ddf",
                  "name": "England vs Congo DR",
                  "streams": [
                    {
                      "id": "st-7858570ddf",
                      "name": "QC",
                      "stream_links": [
                        {
                          "id": "lnk-6cafe33b0c",
                          "name": "Link FHD",
                          "type": "hls",
                          "default": true,
                          "url": "https://ahghndtkyqmm-pull.bpmedialive.com/quechoa/blv1.m3u8",
                          "request_headers": [
                            {
                              "key": "Referer",
                              "value": "https://quechoa10.live/"
                            },
                            {
                              "key": "Origin",
                              "value": "https://quechoa10.live"
                            },
                            {
                              "key": "User-Agent",
                              "value": "Mozilla/5.0"
                            }
                          ]
                        }
                      ]
                    }
                  ]
                }
              ]
            }
          ],
          "org_metadata": {
            "league": "World Cup",
            "team_a": "England",
            "team_b": "Congo DR",
            "logo_a": "https://media.api-sports.io/football/teams/10.png",
            "logo_b": "https://media.api-sports.io/football/teams/1508.png",
            "time": "23:00",
            "date": "01/07",
            "blv": "PUMA, DƯA HẤU, VĂN MINH",
            "is_live": false,
            "sport_slug": "bong-da"
          },
          "image": {
            "padding": 1,
            "background_color": "#ffffff",
            "display": "contain",
            "url": "https://raw.githubusercontent.com/jasminliu98/quechoa-stream/refs/heads/main/thumbs/qc-7858570ddf_3c40b560_20260630.png?v=3c40b560",
            "width": 1600,
            "height": 1200
          }
        }
      ]
    },
    {
      "id": "grp-tennis",
      "name": "🎾 Tennis",
      "display": "vertical",
      "grid_number": 2,
      "enable_detail": false,
      "channels": []
    },
    {
      "id": "grp-cầu-lông",
      "name": "🏸 Cầu Lông",
      "display": "vertical",
      "grid_number": 2,
      "enable_detail": false,
      "channels": []
    },
    {
      "id": "grp-bóng-rổ",
      "name": "🏀 Bóng Rổ",
      "display": "vertical",
      "grid_number": 2,
      "enable_detail": false,
      "channels": []
    },
    {
      "id": "grp-billiards",
      "name": "🎱 Billiards",
      "display": "vertical",
      "grid_number": 2,
      "enable_detail": false,
      "channels": []
    },
    {
      "id": "grp-bóng-chuyền",
      "name": "🏐 Bóng Chuyền (2 LIVE)",
      "display": "vertical",
      "grid_number": 2,
      "enable_detail": false,
      "channels": [
        {
          "id": "bg-d5cec10270",
          "name": "Iran vs Philippines | 10:00 01/07",
          "type": "single",
          "display": "thumbnail-only",
          "enable_detail": false,
          "labels": [
            {
              "text": "🕐 Sắp",
              "position": "top-left",
              "color": "#00000080",
              "text_color": "#aaaaaa"
            }
          ],
          "sources": [
            {
              "id": "src-d5cec10270",
              "name": "BugioTV",
              "contents": [
                {
                  "id": "ct-d5cec10270",
                  "name": "Iran vs Philippines",
                  "streams": [
                    {
                      "id": "st-d5cec10270",
                      "name": "BG",
                      "stream_links": [
                        {
                          "id": "lnk-970b2a547c",
                          "name": "Link FHD",
                          "type": "hls",
                          "default": true,
                          "url": "https://bglive.yarncdn.live/live/bgtv_blv_phaothan/playlist.m3u8",
                          "request_headers": [
                            {
                              "key": "Referer",
                              "value": "https://sv1.bugio9.live/"
                            },
                            {
                              "key": "User-Agent",
                              "value": "Mozilla/5.0"
                            }
                          ]
                        }
                      ]
                    }
                  ]
                }
              ]
            }
          ],
          "org_metadata": {
            "league": "Bóng chuyền U18 Châu Á",
            "team_a": "Iran ",
            "team_b": "Philippines",
            "logo_a": "https://ssl.gstatic.com/onebox/media/sports/logos/optimized/1oq8Fy7ETpBpZNaCA22ArQ_96x96.png",
            "logo_b": "https://ssl.gstatic.com/onebox/media/sports/logos/optimized/SMAJOAEhYfXLrR5oOCzaYg_96x96.png",
            "start_time": "2026-07-01T10:00:00",
            "blv": "BLV Pháo",
            "is_live": false,
            "cate_type": "bongchuyen"
          },
          "image": {
            "padding": 1,
            "background_color": "#ffffff",
            "display": "contain",
            "url": "https://raw.githubusercontent.com/jasminliu98/bugio-stream/refs/heads/main/thumbs/bg-d5cec10270_ff6048a1_20260630.png?v=ff6048a1",
            "width": 1600,
            "height": 1200
          }
        },
        {
          "id": "bg-4f3d7d38d2",
          "name": "Hàn Quốc vs Ấn Độ | 13:00 01/07",
          "type": "single",
          "display": "thumbnail-only",
          "enable_detail": false,
          "labels": [
            {
              "text": "🕐 Sắp",
              "position": "top-left",
              "color": "#00000080",
              "text_color": "#aaaaaa"
            }
          ],
          "sources": [
            {
              "id": "src-4f3d7d38d2",
              "name": "BugioTV",
              "contents": [
                {
                  "id": "ct-4f3d7d38d2",
                  "name": "Hàn Quốc vs Ấn Độ",
                  "streams": [
                    {
                      "id": "st-4f3d7d38d2",
                      "name": "BG",
                      "stream_links": [
                        {
                          "id": "lnk-21936c1c94",
                          "name": "Link FHD",
                          "type": "hls",
                          "default": true,
                          "url": "https://bglive.yarncdn.live/live/bgtv_blv_tieumeo/playlist.m3u8",
                          "request_headers": [
                            {
                              "key": "Referer",
                              "value": "https://sv1.bugio9.live/"
                            },
                            {
                              "key": "User-Agent",
                              "value": "Mozilla/5.0"
                            }
                          ]
                        }
                      ]
                    }
                  ]
                }
              ]
            }
          ],
          "org_metadata": {
            "league": "Bóng chuyền U18 Châu Á",
            "team_a": "Hàn Quốc ",
            "team_b": "Ấn Độ",
            "logo_a": "https://static.flashscore.com/res/image/data/zTP55fFG-bL62vc24.png",
            "logo_b": "https://upload.wikimedia.org/wikipedia/commons/thumb/4/41/Flag_of_India.svg/500px-Flag_of_India.svg.png",
            "start_time": "2026-07-01T13:00:00",
            "blv": "BLV Tiểu Mèo",
            "is_live": false,
            "cate_type": "bongchuyen"
          },
          "image": {
            "padding": 1,
            "background_color": "#ffffff",
            "display": "contain",
            "url": "https://raw.githubusercontent.com/jasminliu98/bugio-stream/refs/heads/main/thumbs/bg-4f3d7d38d2_649a1fc3_20260630.png?v=649a1fc3",
            "width": 1600,
            "height": 1200
          }
        }
      ]
    },
    {
      "id": "grp-đua-xe",
      "name": "🏎️ Đua Xe",
      "display": "vertical",
      "grid_number": 2,
      "enable_detail": false,
      "channels": []
    },
    {
      "id": "grp-bóng-bàn",
      "name": "🏓 Bóng Bàn",
      "display": "vertical",
      "grid_number": 2,
      "enable_detail": false,
      "channels": []
    },
    {
      "id": "grp-võ-thuật",
      "name": "🥊 Võ Thuật",
      "display": "vertical",
      "grid_number": 2,
      "enable_detail": false,
      "channels": []
    },
    {
      "id": "grp-pickleball",
      "name": "🏸 Pickleball",
      "display": "vertical",
      "grid_number": 2,
      "enable_detail": false,
      "channels": []
    }
  ]
}