{
  "id": "allin1-stream",
  "name": "All In 1 Stream",
  "version": "V1.0",
  "color": "#1cb57a",
  "grid_number": 3,
  "description": "This file does not stream any of the included channels, all streaming links are from third-party websites available freely on the internet. This is simply to provide a link to stream, and all content is copyright of their owner.",
  "image": {
    "type": "cover",
    "url": "https://raw.githubusercontent.com/Bigblok-ai/allin1-stream/main/logo.png"
  },
  "groups": [
    {
      "id": "grp-tv-hoiquan",
      "name": "📺 Kênh Truyền Hình (12 LIVE)",
      "display": "vertical",
      "grid_number": 2,
      "enable_detail": false,
      "channels": [
        {
          "id": "tv-0",
          "name": "VTV1",
          "type": "single",
          "display": "thumbnail-only",
          "enable_detail": false,
          "labels": [
            {
              "text": "● LIVE",
              "position": "top-left",
              "color": "#00000080",
              "text_color": "#ff4444"
            }
          ],
          "sources": [
            {
              "id": "src-tv-0-0",
              "name": "Source 1 - fptplay53",
              "contents": [
                {
                  "id": "ct-tv-0-0",
                  "name": "VTV1",
                  "streams": [
                    {
                      "id": "st-tv-0-0",
                      "name": "KT",
                      "stream_links": [
                        {
                          "id": "lnk-tv-0-0",
                          "name": "Link 1",
                          "type": "hls",
                          "default": true,
                          "url": "https://live.fptplay53.net/live/media/vtv1/live247-hls-avc/index.m3u8",
                          "request_headers": [],
                          "drm_type": "",
                          "drm_key": ""
                        }
                      ]
                    }
                  ]
                }
              ]
            },
            {
              "id": "src-tv-0-1",
              "name": "Source 2 - fptplay53",
              "contents": [
                {
                  "id": "ct-tv-0-1",
                  "name": "VTV1",
                  "streams": [
                    {
                      "id": "st-tv-0-1",
                      "name": "KT",
                      "stream_links": [
                        {
                          "id": "lnk-tv-0-1",
                          "name": "Link 2",
                          "type": "hls",
                          "default": false,
                          "url": "https://live.fptplay53.net/live/media/vtv1/live247-hls-avc/vtv1-avc1_5600000=10000-mp4a_131600=20000.m3u8",
                          "request_headers": [],
                          "drm_type": "",
                          "drm_key": ""
                        }
                      ]
                    }
                  ]
                }
              ]
            },
            {
              "id": "src-tv-0-2",
              "name": "Source 3 - dpdns",
              "contents": [
                {
                  "id": "ct-tv-0-2",
                  "name": "VTV1",
                  "streams": [
                    {
                      "id": "st-tv-0-2",
                      "name": "KT",
                      "stream_links": [
                        {
                          "id": "lnk-tv-0-2",
                          "name": "Link 3",
                          "type": "hls",
                          "default": false,
                          "url": "https://toiyeuvietnam.dpdns.org/TuyetDoiKhongKinhDoanh/vtv1-hd/KenhCoBan.m3u8",
                          "request_headers": [],
                          "drm_type": "",
                          "drm_key": ""
                        }
                      ]
                    }
                  ]
                }
              ]
            }
          ],
          "org_metadata": {
            "is_live": true,
            "time": "",
            "team_a": "VTV1",
            "team_b": ""
          },
          "image": {
            "padding": 1,
            "background_color": "#ffffff",
            "display": "contain",
            "url": "https://toiyeuvietnam.dpdns.org/Logo/vtv1-hd/KenhCoBan.png",
            "width": 1600,
            "height": 1200
          }
        },
        {
          "id": "tv-1",
          "name": "VTV2",
          "type": "single",
          "display": "thumbnail-only",
          "enable_detail": false,
          "labels": [
            {
              "text": "● LIVE",
              "position": "top-left",
              "color": "#00000080",
              "text_color": "#ff4444"
            }
          ],
          "sources": [
            {
              "id": "src-tv-1-0",
              "name": "Source 1 - fptplay53",
              "contents": [
                {
                  "id": "ct-tv-1-0",
                  "name": "VTV2",
                  "streams": [
                    {
                      "id": "st-tv-1-0",
                      "name": "KT",
                      "stream_links": [
                        {
                          "id": "lnk-tv-1-0",
                          "name": "Link 1",
                          "type": "hls",
                          "default": true,
                          "url": "https://live.fptplay53.net/live/media/v2abr/live247-hls-avc/index.m3u8",
                          "request_headers": [],
                          "drm_type": "",
                          "drm_key": ""
                        }
                      ]
                    }
                  ]
                }
              ]
            },
            {
              "id": "src-tv-1-1",
              "name": "Source 2 - dpdns",
              "contents": [
                {
                  "id": "ct-tv-1-1",
                  "name": "VTV2",
                  "streams": [
                    {
                      "id": "st-tv-1-1",
                      "name": "KT",
                      "stream_links": [
                        {
                          "id": "lnk-tv-1-1",
                          "name": "Link 2",
                          "type": "hls",
                          "default": false,
                          "url": "https://toiyeuvietnam.dpdns.org/TuyetDoiKhongKinhDoanh/vtv2-hd/KenhCoBan.m3u8",
                          "request_headers": [],
                          "drm_type": "",
                          "drm_key": ""
                        }
                      ]
                    }
                  ]
                }
              ]
            }
          ],
          "org_metadata": {
            "is_live": true,
            "time": "",
            "team_a": "VTV2",
            "team_b": ""
          },
          "image": {
            "padding": 1,
            "background_color": "#ffffff",
            "display": "contain",
            "url": "https://toiyeuvietnam.dpdns.org/Logo/vtv2-hd/KenhCoBan.png",
            "width": 1600,
            "height": 1200
          }
        },
        {
          "id": "tv-2",
          "name": "VTV3",
          "type": "single",
          "display": "thumbnail-only",
          "enable_detail": false,
          "labels": [
            {
              "text": "● LIVE",
              "position": "top-left",
              "color": "#00000080",
              "text_color": "#ff4444"
            }
          ],
          "sources": [
            {
              "id": "src-tv-2-0",
              "name": "Source 1 - fptplay53",
              "contents": [
                {
                  "id": "ct-tv-2-0",
                  "name": "VTV3",
                  "streams": [
                    {
                      "id": "st-tv-2-0",
                      "name": "KT",
                      "stream_links": [
                        {
                          "id": "lnk-tv-2-0",
                          "name": "Link 1",
                          "type": "hls",
                          "default": true,
                          "url": "https://live.fptplay53.net/live/media/v3abr/live247-hls-avc/index.m3u8",
                          "request_headers": [],
                          "drm_type": "",
                          "drm_key": ""
                        }
                      ]
                    }
                  ]
                }
              ]
            },
            {
              "id": "src-tv-2-1",
              "name": "Source 2 - fptplay53",
              "contents": [
                {
                  "id": "ct-tv-2-1",
                  "name": "VTV3",
                  "streams": [
                    {
                      "id": "st-tv-2-1",
                      "name": "KT",
                      "stream_links": [
                        {
                          "id": "lnk-tv-2-1",
                          "name": "Link 2",
                          "type": "hls",
                          "default": false,
                          "url": "https://live.fptplay53.net/live/media/v3abr/live247-hls-avc/v3abr-avc1_5600000=10000-mp4a_131600=20000.m3u8",
                          "request_headers": [],
                          "drm_type": "",
                          "drm_key": ""
                        }
                      ]
                    }
                  ]
                }
              ]
            }
          ],
          "org_metadata": {
            "is_live": true,
            "time": "",
            "team_a": "VTV3",
            "team_b": ""
          },
          "image": {
            "padding": 1,
            "background_color": "#ffffff",
            "display": "contain",
            "url": "https://toiyeuvietnam.dpdns.org/Logo/vtv3-hd/KenhCoBan.png",
            "width": 1600,
            "height": 1200
          }
        },
        {
          "id": "tv-3",
          "name": "VTV5",
          "type": "single",
          "display": "thumbnail-only",
          "enable_detail": false,
          "labels": [
            {
              "text": "● LIVE",
              "position": "top-left",
              "color": "#00000080",
              "text_color": "#ff4444"
            }
          ],
          "sources": [
            {
              "id": "src-tv-3-0",
              "name": "Source 1 - fptplay53",
              "contents": [
                {
                  "id": "ct-tv-3-0",
                  "name": "VTV5",
                  "streams": [
                    {
                      "id": "st-tv-3-0",
                      "name": "KT",
                      "stream_links": [
                        {
                          "id": "lnk-tv-3-0",
                          "name": "Link 1",
                          "type": "hls",
                          "default": true,
                          "url": "https://live.fptplay53.net/live/media/vtv5/live247-hls-avc/vtv5-avc1_5600000=10000-mp4a_131600=20000.m3u8",
                          "request_headers": [],
                          "drm_type": "",
                          "drm_key": ""
                        }
                      ]
                    }
                  ]
                }
              ]
            },
            {
              "id": "src-tv-3-1",
              "name": "Source 2 - fptplay53",
              "contents": [
                {
                  "id": "ct-tv-3-1",
                  "name": "VTV5",
                  "streams": [
                    {
                      "id": "st-tv-3-1",
                      "name": "KT",
                      "stream_links": [
                        {
                          "id": "lnk-tv-3-1",
                          "name": "Link 2",
                          "type": "hls",
                          "default": false,
                          "url": "https://live.fptplay53.net/live/media/vtv5/live247-hls-avc/index.m3u8",
                          "request_headers": [],
                          "drm_type": "",
                          "drm_key": ""
                        }
                      ]
                    }
                  ]
                }
              ]
            }
          ],
          "org_metadata": {
            "is_live": true,
            "time": "",
            "team_a": "VTV5",
            "team_b": ""
          },
          "image": {
            "padding": 1,
            "background_color": "#ffffff",
            "display": "contain",
            "url": "https://toiyeuvietnam.dpdns.org/Logo/vtv5-hd/KenhCoBan.png",
            "width": 1600,
            "height": 1200
          }
        },
        {
          "id": "tv-4",
          "name": "VTV5 Tây Nguyên",
          "type": "single",
          "display": "thumbnail-only",
          "enable_detail": false,
          "labels": [
            {
              "text": "● LIVE",
              "position": "top-left",
              "color": "#00000080",
              "text_color": "#ff4444"
            }
          ],
          "sources": [
            {
              "id": "src-tv-4-0",
              "name": "Source 1 - fptplay53",
              "contents": [
                {
                  "id": "ct-tv-4-0",
                  "name": "VTV5 Tây Nguyên",
                  "streams": [
                    {
                      "id": "st-tv-4-0",
                      "name": "KT",
                      "stream_links": [
                        {
                          "id": "lnk-tv-4-0",
                          "name": "Link 1",
                          "type": "hls",
                          "default": true,
                          "url": "https://live.fptplay53.net/fnxhd1/vtv5taynguyen_vhls.smil/chunklist_b5000000.m3u8",
                          "request_headers": [],
                          "drm_type": "",
                          "drm_key": ""
                        }
                      ]
                    }
                  ]
                }
              ]
            }
          ],
          "org_metadata": {
            "is_live": true,
            "time": "",
            "team_a": "VTV5 Tây Nguyên",
            "team_b": ""
          },
          "image": {
            "padding": 1,
            "background_color": "#ffffff",
            "display": "contain",
            "url": "https://toiyeuvietnam.dpdns.org/Logo/vtv5-tay-nguyen/KenhCoBan.png",
            "width": 1600,
            "height": 1200
          }
        },
        {
          "id": "tv-5",
          "name": "VTV6",
          "type": "single",
          "display": "thumbnail-only",
          "enable_detail": false,
          "labels": [
            {
              "text": "● LIVE",
              "position": "top-left",
              "color": "#00000080",
              "text_color": "#ff4444"
            }
          ],
          "sources": [
            {
              "id": "src-tv-5-0",
              "name": "Source 1 - fptplay53",
              "contents": [
                {
                  "id": "ct-tv-5-0",
                  "name": "VTV6",
                  "streams": [
                    {
                      "id": "st-tv-5-0",
                      "name": "KT",
                      "stream_links": [
                        {
                          "id": "lnk-tv-5-0",
                          "name": "Link 1",
                          "type": "hls",
                          "default": true,
                          "url": "https://live-a.fptplay53.net/live/media/vtv6/live247-hls-avc/index.m3u8",
                          "request_headers": [],
                          "drm_type": "",
                          "drm_key": ""
                        }
                      ]
                    }
                  ]
                }
              ]
            },
            {
              "id": "src-tv-5-1",
              "name": "Source 2 - fptplay53",
              "contents": [
                {
                  "id": "ct-tv-5-1",
                  "name": "VTV6",
                  "streams": [
                    {
                      "id": "st-tv-5-1",
                      "name": "KT",
                      "stream_links": [
                        {
                          "id": "lnk-tv-5-1",
                          "name": "Link 2",
                          "type": "hls",
                          "default": false,
                          "url": "https://live-a.fptplay53.net/live/media/vtv6/live247-hls-avc/vtv6-avc1_5600000=10000-mp4a_131600=20000.m3u8",
                          "request_headers": [],
                          "drm_type": "",
                          "drm_key": ""
                        }
                      ]
                    }
                  ]
                }
              ]
            },
            {
              "id": "src-tv-5-2",
              "name": "Source 3 - dpdns",
              "contents": [
                {
                  "id": "ct-tv-5-2",
                  "name": "VTV6",
                  "streams": [
                    {
                      "id": "st-tv-5-2",
                      "name": "KT",
                      "stream_links": [
                        {
                          "id": "lnk-tv-5-2",
                          "name": "Link 3",
                          "type": "hls",
                          "default": false,
                          "url": "https://toiyeuvietnam.dpdns.org/TuyetDoiKhongKinhDoanh/vtv6-hd/KenhCoBan.m3u8",
                          "request_headers": [],
                          "drm_type": "",
                          "drm_key": ""
                        }
                      ]
                    }
                  ]
                }
              ]
            }
          ],
          "org_metadata": {
            "is_live": true,
            "time": "",
            "team_a": "VTV6",
            "team_b": ""
          },
          "image": {
            "padding": 1,
            "background_color": "#ffffff",
            "display": "contain",
            "url": "https://toiyeuvietnam.dpdns.org/Logo/vtv6-hd-2/KenhBoSung.png",
            "width": 1600,
            "height": 1200
          }
        },
        {
          "id": "tv-6",
          "name": "VTV7",
          "type": "single",
          "display": "thumbnail-only",
          "enable_detail": false,
          "labels": [
            {
              "text": "● LIVE",
              "position": "top-left",
              "color": "#00000080",
              "text_color": "#ff4444"
            }
          ],
          "sources": [
            {
              "id": "src-tv-6-0",
              "name": "Source 1 - fptplay53",
              "contents": [
                {
                  "id": "ct-tv-6-0",
                  "name": "VTV7",
                  "streams": [
                    {
                      "id": "st-tv-6-0",
                      "name": "KT",
                      "stream_links": [
                        {
                          "id": "lnk-tv-6-0",
                          "name": "Link 1",
                          "type": "hls",
                          "default": true,
                          "url": "https://live.fptplay53.net/live/media/v7abr/live247-hls-avc/index.m3u8",
                          "request_headers": [],
                          "drm_type": "",
                          "drm_key": ""
                        }
                      ]
                    }
                  ]
                }
              ]
            },
            {
              "id": "src-tv-6-1",
              "name": "Source 2 - fptplay53",
              "contents": [
                {
                  "id": "ct-tv-6-1",
                  "name": "VTV7",
                  "streams": [
                    {
                      "id": "st-tv-6-1",
                      "name": "KT",
                      "stream_links": [
                        {
                          "id": "lnk-tv-6-1",
                          "name": "Link 2",
                          "type": "hls",
                          "default": false,
                          "url": "https://live.fptplay53.net/live/media/vtv7/live247-hls-avc/vtv7-avc1_5600000=10000-mp4a_131600=20000.m3u8",
                          "request_headers": [],
                          "drm_type": "",
                          "drm_key": ""
                        }
                      ]
                    }
                  ]
                }
              ]
            }
          ],
          "org_metadata": {
            "is_live": true,
            "time": "",
            "team_a": "VTV7",
            "team_b": ""
          },
          "image": {
            "padding": 1,
            "background_color": "#ffffff",
            "display": "contain",
            "url": "https://toiyeuvietnam.dpdns.org/Logo/vtv7-hd/KenhCoBan.png",
            "width": 1600,
            "height": 1200
          }
        },
        {
          "id": "tv-7",
          "name": "VTV9",
          "type": "single",
          "display": "thumbnail-only",
          "enable_detail": false,
          "labels": [
            {
              "text": "● LIVE",
              "position": "top-left",
              "color": "#00000080",
              "text_color": "#ff4444"
            }
          ],
          "sources": [
            {
              "id": "src-tv-7-0",
              "name": "Source 1 - fptplay53",
              "contents": [
                {
                  "id": "ct-tv-7-0",
                  "name": "VTV9",
                  "streams": [
                    {
                      "id": "st-tv-7-0",
                      "name": "KT",
                      "stream_links": [
                        {
                          "id": "lnk-tv-7-0",
                          "name": "Link 1",
                          "type": "hls",
                          "default": true,
                          "url": "https://live.fptplay53.net/live/media/v9abr/live247-hls-avc/index.m3u8",
                          "request_headers": [],
                          "drm_type": "",
                          "drm_key": ""
                        }
                      ]
                    }
                  ]
                }
              ]
            },
            {
              "id": "src-tv-7-1",
              "name": "Source 2 - fptplay53",
              "contents": [
                {
                  "id": "ct-tv-7-1",
                  "name": "VTV9",
                  "streams": [
                    {
                      "id": "st-tv-7-1",
                      "name": "KT",
                      "stream_links": [
                        {
                          "id": "lnk-tv-7-1",
                          "name": "Link 2",
                          "type": "hls",
                          "default": false,
                          "url": "https://live.fptplay53.net/live/media/vtv9/live247-hls-avc/vtv9-avc1_5600000=10000-mp4a_131600=20000.m3u8",
                          "request_headers": [],
                          "drm_type": "",
                          "drm_key": ""
                        }
                      ]
                    }
                  ]
                }
              ]
            },
            {
              "id": "src-tv-7-2",
              "name": "Source 3 - dpdns",
              "contents": [
                {
                  "id": "ct-tv-7-2",
                  "name": "VTV9",
                  "streams": [
                    {
                      "id": "st-tv-7-2",
                      "name": "KT",
                      "stream_links": [
                        {
                          "id": "lnk-tv-7-2",
                          "name": "Link 3",
                          "type": "hls",
                          "default": false,
                          "url": "https://toiyeuvietnam.dpdns.org/TuyetDoiKhongKinhDoanh/vtv9-hd/KenhCoBan.m3u8",
                          "request_headers": [],
                          "drm_type": "",
                          "drm_key": ""
                        }
                      ]
                    }
                  ]
                }
              ]
            }
          ],
          "org_metadata": {
            "is_live": true,
            "time": "",
            "team_a": "VTV9",
            "team_b": ""
          },
          "image": {
            "padding": 1,
            "background_color": "#ffffff",
            "display": "contain",
            "url": "https://toiyeuvietnam.dpdns.org/Logo/vtv9-hd/KenhCoBan.png",
            "width": 1600,
            "height": 1200
          }
        },
        {
          "id": "tv-8",
          "name": "VTV10",
          "type": "single",
          "display": "thumbnail-only",
          "enable_detail": false,
          "labels": [
            {
              "text": "● LIVE",
              "position": "top-left",
              "color": "#00000080",
              "text_color": "#ff4444"
            }
          ],
          "sources": [
            {
              "id": "src-tv-8-0",
              "name": "Source 1 - fptplay53",
              "contents": [
                {
                  "id": "ct-tv-8-0",
                  "name": "VTV10",
                  "streams": [
                    {
                      "id": "st-tv-8-0",
                      "name": "KT",
                      "stream_links": [
                        {
                          "id": "lnk-tv-8-0",
                          "name": "Link 1",
                          "type": "hls",
                          "default": true,
                          "url": "https://live.fptplay53.net/live/media/v10abr/live247-hls-avc/index.m3u8",
                          "request_headers": [],
                          "drm_type": "",
                          "drm_key": ""
                        }
                      ]
                    }
                  ]
                }
              ]
            }
          ],
          "org_metadata": {
            "is_live": true,
            "time": "",
            "team_a": "VTV10",
            "team_b": ""
          },
          "image": {
            "padding": 1,
            "background_color": "#ffffff",
            "display": "contain",
            "url": "https://toiyeuvietnam.dpdns.org/Logo/vtv10-hd/KenhCoBan.png",
            "width": 1600,
            "height": 1200
          }
        },
        {
          "id": "tv-9",
          "name": "HTV Thể Thao",
          "type": "single",
          "display": "thumbnail-only",
          "enable_detail": false,
          "labels": [
            {
              "text": "● LIVE",
              "position": "top-left",
              "color": "#00000080",
              "text_color": "#ff4444"
            }
          ],
          "sources": [
            {
              "id": "src-tv-9-0",
              "name": "Source 1 - fptplay53",
              "contents": [
                {
                  "id": "ct-tv-9-0",
                  "name": "HTV Thể Thao",
                  "streams": [
                    {
                      "id": "st-tv-9-0",
                      "name": "KT",
                      "stream_links": [
                        {
                          "id": "lnk-tv-9-0",
                          "name": "Link 1",
                          "type": "hls",
                          "default": true,
                          "url": "https://live.fptplay53.net/epzhd1/htvcthethao_vhls.smil/chunklist_b5000000.m3u8",
                          "request_headers": [],
                          "drm_type": "",
                          "drm_key": ""
                        }
                      ]
                    }
                  ]
                }
              ]
            },
            {
              "id": "src-tv-9-1",
              "name": "Source 2 - fptplay53",
              "contents": [
                {
                  "id": "ct-tv-9-1",
                  "name": "HTV Thể Thao",
                  "streams": [
                    {
                      "id": "st-tv-9-1",
                      "name": "KT",
                      "stream_links": [
                        {
                          "id": "lnk-tv-9-1",
                          "name": "Link 2",
                          "type": "hls",
                          "default": false,
                          "url": "https://live.fptplay53.net/live/media/htvthethao/live247-hls-avc/htvthethao-avc1_5600000=10000-mp4a_131600=20000.m3u8",
                          "request_headers": [],
                          "drm_type": "",
                          "drm_key": ""
                        }
                      ]
                    }
                  ]
                }
              ]
            }
          ],
          "org_metadata": {
            "is_live": true,
            "time": "",
            "team_a": "HTV Thể Thao",
            "team_b": ""
          },
          "image": {
            "padding": 1,
            "background_color": "#ffffff",
            "display": "contain",
            "url": "https://toiyeuvietnam.dpdns.org/Logo/htv-the-thao/KenhCoBan.png",
            "width": 1600,
            "height": 1200
          }
        },
        {
          "id": "tv-10",
          "name": "TVB Vietnam",
          "type": "single",
          "display": "thumbnail-only",
          "enable_detail": false,
          "labels": [
            {
              "text": "● LIVE",
              "position": "top-left",
              "color": "#00000080",
              "text_color": "#ff4444"
            }
          ],
          "sources": [
            {
              "id": "src-tv-10-0",
              "name": "Source 1 - amagi",
              "contents": [
                {
                  "id": "ct-tv-10-0",
                  "name": "TVB Vietnam",
                  "streams": [
                    {
                      "id": "st-tv-10-0",
                      "name": "KT",
                      "stream_links": [
                        {
                          "id": "lnk-tv-10-0",
                          "name": "Link 1",
                          "type": "hls",
                          "default": true,
                          "url": "https://amg01868-amg01868c3-tvbanywhere-us-4491.playouts.now.amagi.tv/playlist1080p.m3u8",
                          "request_headers": [],
                          "drm_type": "",
                          "drm_key": ""
                        }
                      ]
                    }
                  ]
                }
              ]
            }
          ],
          "org_metadata": {
            "is_live": true,
            "time": "",
            "team_a": "TVB Vietnam",
            "team_b": ""
          },
          "image": {
            "padding": 1,
            "background_color": "#ffffff",
            "display": "contain",
            "url": "https://tvbaw-na.s3.us-west-1.amazonaws.com/hb/TVB%20Vietnam%20Banner_Side.jpg",
            "width": 1600,
            "height": 1200
          }
        },
        {
          "id": "tv-11",
          "name": "HBO",
          "type": "single",
          "display": "thumbnail-only",
          "enable_detail": false,
          "labels": [
            {
              "text": "● LIVE",
              "position": "top-left",
              "color": "#00000080",
              "text_color": "#ff4444"
            }
          ],
          "sources": [
            {
              "id": "src-tv-11-0",
              "name": "Source 1 - mytvnet",
              "contents": [
                {
                  "id": "ct-tv-11-0",
                  "name": "HBO",
                  "streams": [
                    {
                      "id": "st-tv-11-0",
                      "name": "KT",
                      "stream_links": [
                        {
                          "id": "lnk-tv-11-0",
                          "name": "Link 1",
                          "type": "dash",
                          "default": true,
                          "url": "https://s2129134.cdn.mytvnet.vn/pkg20/live_dzones/hbo.smil/manifest.mpd",
                          "request_headers": [
                            {
                              "key": "User-Agent",
                              "value": "Dalvik/2.1.0"
                            }
                          ],
                          "drm_type": "clearkey",
                          "drm_key": {
                            "keys": [
                              {
                                "kty": "oct",
                                "k": "PeDzjc8BSCff1b7Dh0PGog",
                                "kid": "Cd3+PWOGPK+ut50FRrCYqw"
                              }
                            ],
                            "type": "temporary"
                          }
                        }
                      ]
                    }
                  ]
                }
              ]
            }
          ],
          "org_metadata": {
            "is_live": true,
            "time": "",
            "team_a": "HBO",
            "team_b": ""
          },
          "image": {
            "padding": 1,
            "background_color": "#ffffff",
            "display": "contain",
            "url": "https://i.pinimg.com/originals/8b/02/00/8b020050690f955ccb306cdf51324aea.png",
            "width": 1600,
            "height": 1200
          }
        }
      ]
    },
    {
      "id": "grp-bóng-đá",
      "name": "⚽ Bóng Đá (3 LIVE)",
      "display": "vertical",
      "grid_number": 2,
      "enable_detail": false,
      "channels": [
        {
          "id": "gv-4f00e48e77",
          "name": "Green Gully Cavaliers vs Dandenong City SC | 16:30 24/07",
          "type": "single",
          "display": "thumbnail-only",
          "enable_detail": false,
          "labels": [
            {
              "text": "● LIVE",
              "position": "top-left",
              "color": "#00000080",
              "text_color": "#ff4444"
            }
          ],
          "sources": [
            {
              "id": "src-4f00e48e77",
              "name": "GiovangTV",
              "contents": [
                {
                  "id": "ct-4f00e48e77",
                  "name": "Green Gully Cavaliers vs Dandenong City SC",
                  "streams": [
                    {
                      "id": "st-4f00e48e77",
                      "name": "GV",
                      "stream_links": [
                        {
                          "id": "lnk-ba18d33a50",
                          "name": "Số 6",
                          "type": "hls",
                          "default": true,
                          "url": "https://eqr2hdarxfliv.vcdn.cloud/1784611905_hd/1784611905_hd@720p.m3u8",
                          "request_headers": [
                            {
                              "key": "Referer",
                              "value": "https://giovang.store/"
                            },
                            {
                              "key": "User-Agent",
                              "value": "Mozilla/5.0 (Windows NT 10.0; Win64; x64) AppleWebKit/537.36"
                            }
                          ]
                        }
                      ]
                    }
                  ]
                }
              ]
            }
          ],
          "org_metadata": {
            "league": "NPL Victoria Úc",
            "team_a": "Green Gully Cavaliers",
            "team_b": "Dandenong City SC",
            "logo_a": "https://images.keovip88.net/images/teams/green-gully-cavaliers.png",
            "logo_b": "https://images.keovip88.net/images/teams/dandenong-city-sc.png",
            "time": "16:30 24/07",
            "blv": "Số 6",
            "is_live": true,
            "cate_type": "football"
          },
          "image": {
            "padding": 1,
            "background_color": "#ffffff",
            "display": "contain",
            "url": "https://raw.githubusercontent.com/jasminliu98/giovang-stream/refs/heads/main/thumbs/6a581f2d24d46db870b015ae_b0d46089_20260724.png?v=b0d46089",
            "width": 1600,
            "height": 1200
          }
        },
        {
          "id": "gv-07d0b99400",
          "name": "Manly United vs Sydney Olympic | 16:30 24/07",
          "type": "single",
          "display": "thumbnail-only",
          "enable_detail": false,
          "labels": [
            {
              "text": "● LIVE",
              "position": "top-left",
              "color": "#00000080",
              "text_color": "#ff4444"
            }
          ],
          "sources": [
            {
              "id": "src-07d0b99400",
              "name": "GiovangTV",
              "contents": [
                {
                  "id": "ct-07d0b99400",
                  "name": "Manly United vs Sydney Olympic",
                  "streams": [
                    {
                      "id": "st-07d0b99400",
                      "name": "GV",
                      "stream_links": [
                        {
                          "id": "lnk-a8f8f95be8",
                          "name": "Số 5",
                          "type": "hls",
                          "default": true,
                          "url": "https://eqr2hdarxfliv.vcdn.cloud/1784611935_hd/1784611935_hd@720p.m3u8",
                          "request_headers": [
                            {
                              "key": "Referer",
                              "value": "https://giovang.store/"
                            },
                            {
                              "key": "User-Agent",
                              "value": "Mozilla/5.0 (Windows NT 10.0; Win64; x64) AppleWebKit/537.36"
                            }
                          ]
                        }
                      ]
                    }
                  ]
                }
              ]
            }
          ],
          "org_metadata": {
            "league": "NPL NSW Úc",
            "team_a": "Manly United",
            "team_b": "Sydney Olympic",
            "logo_a": "https://images.keovip88.net/images/teams/manly-united.png",
            "logo_b": "https://images.keovip88.net/images/teams/sydney-olympic.png",
            "time": "16:30 24/07",
            "blv": "Số 5",
            "is_live": true,
            "cate_type": "football"
          },
          "image": {
            "padding": 1,
            "background_color": "#ffffff",
            "display": "contain",
            "url": "https://raw.githubusercontent.com/jasminliu98/giovang-stream/refs/heads/main/thumbs/6a581f2d24d46db870b015aa1_60321d69_20260724.png?v=60321d69",
            "width": 1600,
            "height": 1200
          }
        },
        {
          "id": "gv-c734bd00ed",
          "name": "St Albans Saints vs Hume City | 16:30 24/07",
          "type": "single",
          "display": "thumbnail-only",
          "enable_detail": false,
          "labels": [
            {
              "text": "● LIVE",
              "position": "top-left",
              "color": "#00000080",
              "text_color": "#ff4444"
            }
          ],
          "sources": [
            {
              "id": "src-c734bd00ed",
              "name": "GiovangTV",
              "contents": [
                {
                  "id": "ct-c734bd00ed",
                  "name": "St Albans Saints vs Hume City",
                  "streams": [
                    {
                      "id": "st-c734bd00ed",
                      "name": "GV",
                      "stream_links": [
                        {
                          "id": "lnk-c40b7a190d",
                          "name": "Số 2",
                          "type": "hls",
                          "default": true,
                          "url": "https://eqr2hdarxfliv.vcdn.cloud/1784857248_hd/1784857248_hd@720p.m3u8",
                          "request_headers": [
                            {
                              "key": "Referer",
                              "value": "https://giovang.store/"
                            },
                            {
                              "key": "User-Agent",
                              "value": "Mozilla/5.0 (Windows NT 10.0; Win64; x64) AppleWebKit/537.36"
                            }
                          ]
                        }
                      ]
                    }
                  ]
                }
              ]
            }
          ],
          "org_metadata": {
            "league": "NPL Victoria Úc",
            "team_a": "St Albans Saints",
            "team_b": "Hume City",
            "logo_a": "https://images.keovip88.net/images/teams/st-albans-saints.png",
            "logo_b": "https://images.keovip88.net/images/teams/hume-city.png",
            "time": "16:30 24/07",
            "blv": "Số 2",
            "is_live": true,
            "cate_type": "football"
          },
          "image": {
            "padding": 1,
            "background_color": "#ffffff",
            "display": "contain",
            "url": "https://raw.githubusercontent.com/jasminliu98/giovang-stream/refs/heads/main/thumbs/6a581f2d24d46db870b015bd_25711086_20260724.png?v=25711086",
            "width": 1600,
            "height": 1200
          }
        },
        {
          "id": "gv-ed8aeac22f",
          "name": "Gimhae City FC vs Cheongju Jikji FC | 17:30 24/07",
          "type": "single",
          "display": "thumbnail-only",
          "enable_detail": false,
          "labels": [
            {
              "text": "🕐 Sắp",
              "position": "top-left",
              "color": "#00000080",
              "text_color": "#aaaaaa"
            }
          ],
          "sources": [
            {
              "id": "src-ed8aeac22f",
              "name": "GiovangTV",
              "contents": [
                {
                  "id": "ct-ed8aeac22f",
                  "name": "Gimhae City FC vs Cheongju Jikji FC",
                  "streams": [
                    {
                      "id": "st-ed8aeac22f",
                      "name": "GV",
                      "stream_links": [
                        {
                          "id": "lnk-e54940f132",
                          "name": "Số 17",
                          "type": "hls",
                          "default": true,
                          "url": "https://eqr2hdarxfliv.vcdn.cloud/1784611984_hd/1784611984_hd@720p.m3u8",
                          "request_headers": [
                            {
                              "key": "Referer",
                              "value": "https://giovang.store/"
                            },
                            {
                              "key": "User-Agent",
                              "value": "Mozilla/5.0 (Windows NT 10.0; Win64; x64) AppleWebKit/537.36"
                            }
                          ]
                        }
                      ]
                    }
                  ]
                }
              ]
            }
          ],
          "org_metadata": {
            "league": "K League 2 Hàn Quốc",
            "team_a": "Gimhae City FC",
            "team_b": "Cheongju Jikji FC",
            "logo_a": "https://images.keovip88.net/images/teams/gimhae-city.png",
            "logo_b": "https://images.keovip88.net/images/teams/chungbuk-cheongju.png",
            "time": "17:30 24/07",
            "blv": "Số 17",
            "is_live": false,
            "cate_type": "football"
          },
          "image": {
            "padding": 1,
            "background_color": "#ffffff",
            "display": "contain",
            "url": "https://raw.githubusercontent.com/jasminliu98/giovang-stream/refs/heads/main/thumbs/6a581f2d24d46db870b015e9_e4a75e90_20260724.png?v=e4a75e90",
            "width": 1600,
            "height": 1200
          }
        },
        {
          "id": "gv-dfdbf034f2",
          "name": "Cambodia vs Singapore | 19:00 24/07",
          "type": "single",
          "display": "thumbnail-only",
          "enable_detail": false,
          "labels": [
            {
              "text": "🕐 Sắp",
              "position": "top-left",
              "color": "#00000080",
              "text_color": "#aaaaaa"
            }
          ],
          "sources": [
            {
              "id": "src-dfdbf034f2",
              "name": "GiovangTV",
              "contents": [
                {
                  "id": "ct-dfdbf034f2",
                  "name": "Cambodia vs Singapore",
                  "streams": [
                    {
                      "id": "st-dfdbf034f2",
                      "name": "GV",
                      "stream_links": [
                        {
                          "id": "lnk-eea08b8200",
                          "name": "Số 6",
                          "type": "hls",
                          "default": true,
                          "url": "https://eqr2hdarxfliv.vcdn.cloud/1784612029_hd/1784612029_hd@720p.m3u8",
                          "request_headers": [
                            {
                              "key": "Referer",
                              "value": "https://giovang.store/"
                            },
                            {
                              "key": "User-Agent",
                              "value": "Mozilla/5.0 (Windows NT 10.0; Win64; x64) AppleWebKit/537.36"
                            }
                          ]
                        }
                      ]
                    }
                  ]
                }
              ]
            }
          ],
          "org_metadata": {
            "league": "Asia - ASEAN Championship",
            "team_a": "Cambodia",
            "team_b": "Singapore",
            "logo_a": "https://static.flashscore.com/res/image/data/v7hbfWAr-0pcoctv9.png",
            "logo_b": "https://static.flashscore.com/res/image/data/YJN4hmHG-Qq89lvZJ.png",
            "time": "19:00 24/07",
            "blv": "Số 6",
            "is_live": false,
            "cate_type": "football"
          },
          "image": {
            "padding": 1,
            "background_color": "#ffffff",
            "display": "contain",
            "url": "https://raw.githubusercontent.com/jasminliu98/giovang-stream/refs/heads/main/thumbs/cs36y6i6iyo2_349398dd_20260724.png?v=349398dd",
            "width": 1600,
            "height": 1200
          }
        },
        {
          "id": "gv-03aca3f864",
          "name": "Timor-Leste vs Vietnam | 20:30 24/07",
          "type": "single",
          "display": "thumbnail-only",
          "enable_detail": false,
          "labels": [
            {
              "text": "🕐 Sắp",
              "position": "top-left",
              "color": "#00000080",
              "text_color": "#aaaaaa"
            }
          ],
          "sources": [
            {
              "id": "src-03aca3f864",
              "name": "GiovangTV",
              "contents": [
                {
                  "id": "ct-03aca3f864",
                  "name": "Timor-Leste vs Vietnam",
                  "streams": [
                    {
                      "id": "st-03aca3f864",
                      "name": "GV",
                      "stream_links": [
                        {
                          "id": "lnk-906eab1323",
                          "name": "Số 5",
                          "type": "hls",
                          "default": true,
                          "url": "https://eqr2hdarxfliv.vcdn.cloud/1784612250_hd/1784612250_hd@720p.m3u8",
                          "request_headers": [
                            {
                              "key": "Referer",
                              "value": "https://giovang.store/"
                            },
                            {
                              "key": "User-Agent",
                              "value": "Mozilla/5.0 (Windows NT 10.0; Win64; x64) AppleWebKit/537.36"
                            }
                          ]
                        },
                        {
                          "id": "lnk-46c49e610b",
                          "name": "Số 2",
                          "type": "hls",
                          "default": false,
                          "url": "https://eqr2hdarxfliv.vcdn.cloud/1784612301_hd/1784612301_hd@720p.m3u8",
                          "request_headers": [
                            {
                              "key": "Referer",
                              "value": "https://giovang.store/"
                            },
                            {
                              "key": "User-Agent",
                              "value": "Mozilla/5.0 (Windows NT 10.0; Win64; x64) AppleWebKit/537.36"
                            }
                          ]
                        }
                      ]
                    }
                  ]
                }
              ]
            }
          ],
          "org_metadata": {
            "league": "Asia - ASEAN Championship",
            "team_a": "Timor-Leste",
            "team_b": "Vietnam",
            "logo_a": "https://static.flashscore.com/res/image/data/GtYFHjzB-vTJwRqL9.png",
            "logo_b": "https://static.flashscore.com/res/image/data/rZCKbaFa-QHeKqeWC.png",
            "time": "20:30 24/07",
            "blv": "Số 5, Số 2",
            "is_live": false,
            "cate_type": "football"
          },
          "image": {
            "padding": 1,
            "background_color": "#ffffff",
            "display": "contain",
            "url": "https://raw.githubusercontent.com/jasminliu98/giovang-stream/refs/heads/main/thumbs/ztvs40xdvphu_bce5505d_20260724.png?v=bce5505d",
            "width": 1600,
            "height": 1200
          }
        }
      ]
    },
    {
      "id": "grp-tennis",
      "name": "🎾 Tennis",
      "display": "vertical",
      "grid_number": 2,
      "enable_detail": false,
      "channels": []
    },
    {
      "id": "grp-cầu-lông",
      "name": "🏸 Cầu Lông",
      "display": "vertical",
      "grid_number": 2,
      "enable_detail": false,
      "channels": []
    },
    {
      "id": "grp-bóng-rổ",
      "name": "🏀 Bóng Rổ (2 LIVE)",
      "display": "vertical",
      "grid_number": 2,
      "enable_detail": false,
      "channels": [
        {
          "id": "gv-9e040fb140",
          "name": "Magnolia Hotshots vs Meralco Bolts | 16:15 24/07",
          "type": "single",
          "display": "thumbnail-only",
          "enable_detail": false,
          "labels": [
            {
              "text": "● LIVE",
              "position": "top-left",
              "color": "#00000080",
              "text_color": "#ff4444"
            }
          ],
          "sources": [
            {
              "id": "src-9e040fb140",
              "name": "GiovangTV",
              "contents": [
                {
                  "id": "ct-9e040fb140",
                  "name": "Magnolia Hotshots vs Meralco Bolts",
                  "streams": [
                    {
                      "id": "st-9e040fb140",
                      "name": "GV",
                      "stream_links": [
                        {
                          "id": "lnk-52e009b4ef",
                          "name": "Số 12",
                          "type": "hls",
                          "default": true,
                          "url": "https://eqr2hdarxfliv.vcdn.cloud/1784856951_hd/1784856951_hd@720p.m3u8",
                          "request_headers": [
                            {
                              "key": "Referer",
                              "value": "https://giovang.store/"
                            },
                            {
                              "key": "User-Agent",
                              "value": "Mozilla/5.0 (Windows NT 10.0; Win64; x64) AppleWebKit/537.36"
                            }
                          ]
                        }
                      ]
                    }
                  ]
                }
              ]
            }
          ],
          "org_metadata": {
            "league": "PBA",
            "team_a": "Magnolia Hotshots",
            "team_b": "Meralco Bolts",
            "logo_a": "https://static.flashscore.com/res/image/data/jw4MZXYA-UiVdRBAg.png",
            "logo_b": "https://static.flashscore.com/res/image/data/EiX7h4yS-ddhMe2Bk.png",
            "time": "16:15 24/07",
            "blv": "Số 12",
            "is_live": true,
            "cate_type": "basketball"
          },
          "image": {
            "padding": 1,
            "background_color": "#ffffff",
            "display": "contain",
            "url": "https://raw.githubusercontent.com/jasminliu98/giovang-stream/refs/heads/main/thumbs/dfcrv7zkl0h7_ce1d42b3_20260724.png?v=ce1d42b3",
            "width": 1600,
            "height": 1200
          }
        },
        {
          "id": "gv-39e4f4d166",
          "name": "Batang Kankaloo vs Basilan Viva Portmasters | 17:00 24/07",
          "type": "single",
          "display": "thumbnail-only",
          "enable_detail": false,
          "labels": [
            {
              "text": "● LIVE",
              "position": "top-left",
              "color": "#00000080",
              "text_color": "#ff4444"
            }
          ],
          "sources": [
            {
              "id": "src-39e4f4d166",
              "name": "GiovangTV",
              "contents": [
                {
                  "id": "ct-39e4f4d166",
                  "name": "Batang Kankaloo vs Basilan Viva Portmasters",
                  "streams": [
                    {
                      "id": "st-39e4f4d166",
                      "name": "GV",
                      "stream_links": [
                        {
                          "id": "lnk-713a768e9b",
                          "name": "Số 3",
                          "type": "hls",
                          "default": true,
                          "url": "https://eqr2hdarxfliv.vcdn.cloud/1784857034_hd/1784857034_hd@720p.m3u8",
                          "request_headers": [
                            {
                              "key": "Referer",
                              "value": "https://giovang.store/"
                            },
                            {
                              "key": "User-Agent",
                              "value": "Mozilla/5.0 (Windows NT 10.0; Win64; x64) AppleWebKit/537.36"
                            }
                          ]
                        }
                      ]
                    }
                  ]
                }
              ]
            }
          ],
          "org_metadata": {
            "league": "Philippines MPBL",
            "team_a": "Batang Kankaloo",
            "team_b": "Basilan Viva Portmasters",
            "logo_a": "https://nba.titan007.com/files/team/1hy0b3awkn2a.png",
            "logo_b": "https://nba.titan007.com/files/team/1k2p751yht1b.png",
            "time": "17:00 24/07",
            "blv": "Số 3",
            "is_live": true,
            "cate_type": "basketball"
          },
          "image": {
            "padding": 1,
            "background_color": "#ffffff",
            "display": "contain",
            "url": "https://raw.githubusercontent.com/jasminliu98/giovang-stream/refs/heads/main/thumbs/39781274_f560e52f_20260724.png?v=f560e52f",
            "width": 1600,
            "height": 1200
          }
        },
        {
          "id": "gv-148ed38eab",
          "name": "Quezon City TODA AKSYON vs Zamboanga Familys Brand Sardines | 19:00 23/07",
          "type": "single",
          "display": "thumbnail-only",
          "enable_detail": false,
          "labels": [
            {
              "text": "🕐 Sắp",
              "position": "top-left",
              "color": "#00000080",
              "text_color": "#aaaaaa"
            }
          ],
          "sources": [
            {
              "id": "src-148ed38eab",
              "name": "GiovangTV",
              "contents": [
                {
                  "id": "ct-148ed38eab",
                  "name": "Quezon City TODA AKSYON vs Zamboanga Familys Brand Sardines",
                  "streams": [
                    {
                      "id": "st-148ed38eab",
                      "name": "GV",
                      "stream_links": [
                        {
                          "id": "lnk-a4507462db",
                          "name": "Số 1",
                          "type": "hls",
                          "default": true,
                          "url": "https://eqr2hdarxfliv.vcdn.cloud/1784735781_hd/1784735781_hd@720p.m3u8",
                          "request_headers": [
                            {
                              "key": "Referer",
                              "value": "https://giovang.store/"
                            },
                            {
                              "key": "User-Agent",
                              "value": "Mozilla/5.0 (Windows NT 10.0; Win64; x64) AppleWebKit/537.36"
                            }
                          ]
                        }
                      ]
                    }
                  ]
                }
              ]
            }
          ],
          "org_metadata": {
            "league": "Philippines MPBL",
            "team_a": "Quezon City TODA AKSYON",
            "team_b": "Zamboanga Familys Brand Sardines",
            "logo_a": "https://nba.titan007.com/files/team/1hqmpec8xc27.png",
            "logo_b": "https://nba.titan007.com/files/team/1khmtt4s6g2x.png",
            "time": "19:00 23/07",
            "blv": "Số 1",
            "is_live": false,
            "cate_type": "basketball"
          },
          "image": {
            "padding": 1,
            "background_color": "#ffffff",
            "display": "contain",
            "url": "https://raw.githubusercontent.com/jasminliu98/giovang-stream/refs/heads/main/thumbs/28051273_acb77106_20260724.png?v=acb77106",
            "width": 1600,
            "height": 1200
          }
        },
        {
          "id": "gv-fd28128769",
          "name": "Blackwater Bossing vs Barangay Ginebra San Miguel | 18:30 24/07",
          "type": "single",
          "display": "thumbnail-only",
          "enable_detail": false,
          "labels": [
            {
              "text": "🕐 Sắp",
              "position": "top-left",
              "color": "#00000080",
              "text_color": "#aaaaaa"
            }
          ],
          "sources": [
            {
              "id": "src-fd28128769",
              "name": "GiovangTV",
              "contents": [
                {
                  "id": "ct-fd28128769",
                  "name": "Blackwater Bossing vs Barangay Ginebra San Miguel",
                  "streams": [
                    {
                      "id": "st-fd28128769",
                      "name": "GV",
                      "stream_links": [
                        {
                          "id": "lnk-9f8fd1b8da",
                          "name": "Số 9",
                          "type": "hls",
                          "default": true,
                          "url": "https://eqr2hdarxfliv.vcdn.cloud/1784857087_hd/1784857087_hd@720p.m3u8",
                          "request_headers": [
                            {
                              "key": "Referer",
                              "value": "https://giovang.store/"
                            },
                            {
                              "key": "User-Agent",
                              "value": "Mozilla/5.0 (Windows NT 10.0; Win64; x64) AppleWebKit/537.36"
                            }
                          ]
                        }
                      ]
                    }
                  ]
                }
              ]
            }
          ],
          "org_metadata": {
            "league": "Philippines PBA Governors'' Cup",
            "team_a": "Blackwater Bossing",
            "team_b": "Barangay Ginebra San Miguel",
            "logo_a": "https://static.flashscore.com/res/image/data/EVvVj6ZA-YJ4KHuBj.png",
            "logo_b": "https://static.flashscore.com/res/image/data/hWf7PfGG-67i7cfzM.png",
            "time": "18:30 24/07",
            "blv": "Số 9",
            "is_live": false,
            "cate_type": "basketball"
          },
          "image": {
            "padding": 1,
            "background_color": "#ffffff",
            "display": "contain",
            "url": "https://raw.githubusercontent.com/jasminliu98/giovang-stream/refs/heads/main/thumbs/cwhfp3ggvac0_a10e4602_20260724.png?v=a10e4602",
            "width": 1600,
            "height": 1200
          }
        },
        {
          "id": "gv-6cd0f201bb",
          "name": "Batangas City Athletics vs Rizal Golden Coolers | 19:00 24/07",
          "type": "single",
          "display": "thumbnail-only",
          "enable_detail": false,
          "labels": [
            {
              "text": "🕐 Sắp",
              "position": "top-left",
              "color": "#00000080",
              "text_color": "#aaaaaa"
            }
          ],
          "sources": [
            {
              "id": "src-6cd0f201bb",
              "name": "GiovangTV",
              "contents": [
                {
                  "id": "ct-6cd0f201bb",
                  "name": "Batangas City Athletics vs Rizal Golden Coolers",
                  "streams": [
                    {
                      "id": "st-6cd0f201bb",
                      "name": "GV",
                      "stream_links": [
                        {
                          "id": "lnk-eb59696d75",
                          "name": "Số 3",
                          "type": "hls",
                          "default": true,
                          "url": "https://eqr2hdarxfliv.vcdn.cloud/1784857146_hd/1784857146_hd@720p.m3u8",
                          "request_headers": [
                            {
                              "key": "Referer",
                              "value": "https://giovang.store/"
                            },
                            {
                              "key": "User-Agent",
                              "value": "Mozilla/5.0 (Windows NT 10.0; Win64; x64) AppleWebKit/537.36"
                            }
                          ]
                        }
                      ]
                    }
                  ]
                }
              ]
            }
          ],
          "org_metadata": {
            "league": "Philippines MPBL",
            "team_a": "Batangas City Athletics",
            "team_b": "Rizal Golden Coolers",
            "logo_a": "https://nba.titan007.com/files/team/1kpw5n7f75x.png",
            "logo_b": "https://nba.titan007.com/files/team/1k2p751yh81j.png",
            "time": "19:00 24/07",
            "blv": "Số 3",
            "is_live": false,
            "cate_type": "basketball"
          },
          "image": {
            "padding": 1,
            "background_color": "#ffffff",
            "display": "contain",
            "url": "https://raw.githubusercontent.com/jasminliu98/giovang-stream/refs/heads/main/thumbs/13300275_59053487_20260724.png?v=59053487",
            "width": 1600,
            "height": 1200
          }
        },
        {
          "id": "gv-7c22dfc0a5",
          "name": "Winnipeg Sea Bears vs Hamilton Honey Badgers | 02:30 26/07",
          "type": "single",
          "display": "thumbnail-only",
          "enable_detail": false,
          "labels": [
            {
              "text": "🕐 Sắp",
              "position": "top-left",
              "color": "#00000080",
              "text_color": "#aaaaaa"
            }
          ],
          "sources": [
            {
              "id": "src-7c22dfc0a5",
              "name": "GiovangTV",
              "contents": [
                {
                  "id": "ct-7c22dfc0a5",
                  "name": "Winnipeg Sea Bears vs Hamilton Honey Badgers",
                  "streams": [
                    {
                      "id": "st-7c22dfc0a5",
                      "name": "GV",
                      "stream_links": [
                        {
                          "id": "lnk-0fdbb98101",
                          "name": "Số 3",
                          "type": "hls",
                          "default": true,
                          "url": "https://eqr2hdarxfliv.vcdn.cloud/1784882208_hd/1784882208_hd@720p.m3u8",
                          "request_headers": [
                            {
                              "key": "Referer",
                              "value": "https://giovang.store/"
                            },
                            {
                              "key": "User-Agent",
                              "value": "Mozilla/5.0 (Windows NT 10.0; Win64; x64) AppleWebKit/537.36"
                            }
                          ]
                        }
                      ]
                    }
                  ]
                }
              ]
            }
          ],
          "org_metadata": {
            "league": "Canada EBL",
            "team_a": "Winnipeg Sea Bears",
            "team_b": "Hamilton Honey Badgers",
            "logo_a": "https://nba.titan007.com/files/team/1j0q1h99xj3.png",
            "logo_b": "https://nba.titan007.com/files/team/1krwk9x2dme.png",
            "time": "02:30 26/07",
            "blv": "Số 3",
            "is_live": false,
            "cate_type": "basketball"
          },
          "image": {
            "padding": 1,
            "background_color": "#ffffff",
            "display": "contain",
            "url": "https://raw.githubusercontent.com/jasminliu98/giovang-stream/refs/heads/main/thumbs/24351272_5dae262a_20260724.png?v=5dae262a",
            "width": 1600,
            "height": 1200
          }
        },
        {
          "id": "gv-e6b9bd7243",
          "name": "NLEX Road Warriors vs San Miguel Beermen | 16:15 26/07",
          "type": "single",
          "display": "thumbnail-only",
          "enable_detail": false,
          "labels": [
            {
              "text": "🕐 Sắp",
              "position": "top-left",
              "color": "#00000080",
              "text_color": "#aaaaaa"
            }
          ],
          "sources": [
            {
              "id": "src-e6b9bd7243",
              "name": "GiovangTV",
              "contents": [
                {
                  "id": "ct-e6b9bd7243",
                  "name": "NLEX Road Warriors vs San Miguel Beermen",
                  "streams": [
                    {
                      "id": "st-e6b9bd7243",
                      "name": "GV",
                      "stream_links": [
                        {
                          "id": "lnk-71af7c52d3",
                          "name": "Số 4",
                          "type": "hls",
                          "default": true,
                          "url": "https://eqr2hdarxfliv.vcdn.cloud/1784775667_hd/1784775667_hd@720p.m3u8",
                          "request_headers": [
                            {
                              "key": "Referer",
                              "value": "https://giovang.store/"
                            },
                            {
                              "key": "User-Agent",
                              "value": "Mozilla/5.0 (Windows NT 10.0; Win64; x64) AppleWebKit/537.36"
                            }
                          ]
                        }
                      ]
                    }
                  ]
                }
              ]
            }
          ],
          "org_metadata": {
            "league": "Philippines PBA Governors'' Cup",
            "team_a": "NLEX Road Warriors",
            "team_b": "San Miguel Beermen",
            "logo_a": "https://static.flashscore.com/res/image/data/2agQKghl-4EPybus0.png",
            "logo_b": "https://static.flashscore.com/res/image/data/jeSijRyS-xrx6DBl6.png",
            "time": "16:15 26/07",
            "blv": "Số 4",
            "is_live": false,
            "cate_type": "basketball"
          },
          "image": {
            "padding": 1,
            "background_color": "#ffffff",
            "display": "contain",
            "url": "https://raw.githubusercontent.com/jasminliu98/giovang-stream/refs/heads/main/thumbs/sdsjsxk985kr_594370c5_20260724.png?v=594370c5",
            "width": 1600,
            "height": 1200
          }
        },
        {
          "id": "gv-dbad438df4",
          "name": "Barangay Gibebra San Miguel vs Rain or Shine Elasto Painters | 18:30 26/07",
          "type": "single",
          "display": "thumbnail-only",
          "enable_detail": false,
          "labels": [
            {
              "text": "🕐 Sắp",
              "position": "top-left",
              "color": "#00000080",
              "text_color": "#aaaaaa"
            }
          ],
          "sources": [
            {
              "id": "src-dbad438df4",
              "name": "GiovangTV",
              "contents": [
                {
                  "id": "ct-dbad438df4",
                  "name": "Barangay Gibebra San Miguel vs Rain or Shine Elasto Painters",
                  "streams": [
                    {
                      "id": "st-dbad438df4",
                      "name": "GV",
                      "stream_links": [
                        {
                          "id": "lnk-f61512dff9",
                          "name": "Số 4",
                          "type": "hls",
                          "default": true,
                          "url": "https://eqr2hdarxfliv.vcdn.cloud/1784775775_hd/1784775775_hd@720p.m3u8",
                          "request_headers": [
                            {
                              "key": "Referer",
                              "value": "https://giovang.store/"
                            },
                            {
                              "key": "User-Agent",
                              "value": "Mozilla/5.0 (Windows NT 10.0; Win64; x64) AppleWebKit/537.36"
                            }
                          ]
                        }
                      ]
                    }
                  ]
                }
              ]
            }
          ],
          "org_metadata": {
            "league": "Philippines PBA Governors'' Cup",
            "team_a": "Barangay Gibebra San Miguel",
            "team_b": "Rain or Shine Elasto Painters",
            "logo_a": "https://static.flashscore.com/res/image/data/hWf7PfGG-67i7cfzM.png",
            "logo_b": "https://static.flashscore.com/res/image/data/WjIooAEG-CvPI3PRl.png",
            "time": "18:30 26/07",
            "blv": "Số 4",
            "is_live": false,
            "cate_type": "basketball"
          },
          "image": {
            "padding": 1,
            "background_color": "#ffffff",
            "display": "contain",
            "url": "https://raw.githubusercontent.com/jasminliu98/giovang-stream/refs/heads/main/thumbs/pi5mew2x22ua_eb3bdb7b_20260724.png?v=eb3bdb7b",
            "width": 1600,
            "height": 1200
          }
        }
      ]
    },
    {
      "id": "grp-billiards",
      "name": "🎱 Billiards (1 LIVE)",
      "display": "vertical",
      "grid_number": 2,
      "enable_detail": false,
      "channels": [
        {
          "id": "chtv-023292cde6",
          "name": "Thừa Văn Phúc vs đối áo đen | Kèn Kèn",
          "type": "single",
          "display": "thumbnail-only",
          "enable_detail": false,
          "labels": [
            {
              "text": "LIVE",
              "position": "top-left",
              "color": "#00000080",
              "text_color": "#ff4444"
            }
          ],
          "sources": [
            {
              "id": "src-023292cde6",
              "name": "ChoangTV",
              "contents": [
                {
                  "id": "ct-023292cde6",
                  "name": "Thừa Văn Phúc vs đối áo đen",
                  "streams": [
                    {
                      "id": "st-023292cde6",
                      "name": "CHTV",
                      "stream_links": [
                        {
                          "id": "lnk-023292cde6",
                          "name": "Kèn Kèn",
                          "type": "hls",
                          "default": true,
                          "url": "https://cdn.sports-cas889abxfileposo.site/live/live5163/index.m3u8",
                          "request_headers": [
                            {
                              "key": "Referer",
                              "value": "https://choangtv18.com/"
                            },
                            {
                              "key": "User-Agent",
                              "value": "Mozilla/5.0 (Windows NT 10.0; Win64; x64) AppleWebKit/537.36"
                            }
                          ]
                        }
                      ]
                    }
                  ]
                }
              ]
            }
          ],
          "org_metadata": {
            "league": "bida top top",
            "team_a": "Thừa Văn Phúc",
            "team_b": "đối áo đen",
            "logo_a": "https://cdn-choangtv.com/img/logo/1765417529949_táº£i xuá»ng.png",
            "logo_b": "https://cdn-choangtv.com/img/logo/1765417529949_táº£i xuá»ng.png",
            "time": "16:48 24/07",
            "caster": "Kèn Kèn",
            "score": "2-2",
            "is_live": true,
            "hot": true
          },
          "image": {
            "padding": 1,
            "background_color": "#ffffff",
            "display": "contain",
            "url": "https://raw.githubusercontent.com/jasminliu98/choang-stream/refs/heads/main/thumbs/chtv-023292cde6_999eac8a_20260724.png?v=999eac8a",
            "width": 1600,
            "height": 1200
          }
        },
        {
          "id": "chtv-57137483f5",
          "name": "Yoshida Kosei vs Liu Junchao | 18:30 24/07 | Lee Min Hoo",
          "type": "single",
          "display": "thumbnail-only",
          "enable_detail": false,
          "labels": [
            {
              "text": "SAP",
              "position": "top-left",
              "color": "#00000080",
              "text_color": "#aaaaaa"
            }
          ],
          "sources": [
            {
              "id": "src-57137483f5",
              "name": "ChoangTV",
              "contents": [
                {
                  "id": "ct-57137483f5",
                  "name": "Yoshida Kosei vs Liu Junchao",
                  "streams": [
                    {
                      "id": "st-57137483f5",
                      "name": "CHTV",
                      "stream_links": [
                        {
                          "id": "lnk-57137483f5",
                          "name": "Lee Min Hoo",
                          "type": "hls",
                          "default": true,
                          "url": "https://cdn.sports-cas889abxfileposo.site/live/live4974/index.m3u8",
                          "request_headers": [
                            {
                              "key": "Referer",
                              "value": "https://choangtv18.com/"
                            },
                            {
                              "key": "User-Agent",
                              "value": "Mozilla/5.0 (Windows NT 10.0; Win64; x64) AppleWebKit/537.36"
                            }
                          ]
                        }
                      ]
                    }
                  ]
                }
              ]
            }
          ],
          "org_metadata": {
            "league": "Trận 1 The Inner Circle 23",
            "team_a": "Yoshida Kosei",
            "team_b": "Liu Junchao",
            "logo_a": "https://cdn-choangtv.com/img/logo/1784577438291_Yoshida Kosei.png",
            "logo_b": "https://cdn-choangtv.com/img/logo/1784577483256_Liu Junchao.png",
            "time": "18:30 24/07",
            "caster": "Lee Min Hoo",
            "score": "0-0",
            "is_live": false,
            "hot": true
          },
          "image": {
            "padding": 1,
            "background_color": "#ffffff",
            "display": "contain",
            "url": "https://raw.githubusercontent.com/jasminliu98/choang-stream/refs/heads/main/thumbs/chtv-57137483f5_b0fa6524_20260724.png?v=b0fa6524",
            "width": 1600,
            "height": 1200
          }
        }
      ]
    },
    {
      "id": "grp-bóng-chuyền",
      "name": "🏐 Bóng Chuyền (1 LIVE)",
      "display": "vertical",
      "grid_number": 2,
      "enable_detail": false,
      "channels": [
        {
          "id": "gv-f93a84efe4",
          "name": "Việt Nam vs Myanmar | 15:30 24/07",
          "type": "single",
          "display": "thumbnail-only",
          "enable_detail": false,
          "labels": [
            {
              "text": "● LIVE",
              "position": "top-left",
              "color": "#00000080",
              "text_color": "#ff4444"
            }
          ],
          "sources": [
            {
              "id": "src-f93a84efe4",
              "name": "GiovangTV",
              "contents": [
                {
                  "id": "ct-f93a84efe4",
                  "name": "Việt Nam vs Myanmar",
                  "streams": [
                    {
                      "id": "st-f93a84efe4",
                      "name": "GV",
                      "stream_links": [
                        {
                          "id": "lnk-e07a9dff23",
                          "name": "Số 8",
                          "type": "hls",
                          "default": true,
                          "url": "https://eqr2hdarxfliv.vcdn.cloud/1784856817_hd/1784856817_hd@720p.m3u8",
                          "request_headers": [
                            {
                              "key": "Referer",
                              "value": "https://giovang.store/"
                            },
                            {
                              "key": "User-Agent",
                              "value": "Mozilla/5.0 (Windows NT 10.0; Win64; x64) AppleWebKit/537.36"
                            }
                          ]
                        }
                      ]
                    }
                  ]
                }
              ]
            }
          ],
          "org_metadata": {
            "league": "Sea V Cup",
            "team_a": "Việt Nam",
            "team_b": "Myanmar",
            "logo_a": "https://static.flashscore.com/res/image/data/AXfz4vDa-8xwT7BCP.png",
            "logo_b": "https://static.flashscore.com/res/image/data/pd29lpeM-8xwT7BCP.png",
            "time": "15:30 24/07",
            "blv": "Số 8",
            "is_live": true,
            "cate_type": "bongchuyen"
          },
          "image": {
            "padding": 1,
            "background_color": "#ffffff",
            "display": "contain",
            "url": "https://raw.githubusercontent.com/jasminliu98/giovang-stream/refs/heads/main/thumbs/vytmref4riol_81da0a9c_20260724.png?v=81da0a9c",
            "width": 1600,
            "height": 1200
          }
        }
      ]
    },
    {
      "id": "grp-đua-xe",
      "name": "🏎️ Đua Xe",
      "display": "vertical",
      "grid_number": 2,
      "enable_detail": false,
      "channels": [
        {
          "id": "gv-9e78b587fe",
          "name": "Formula 1 vs Belgian Grand Prix 2026 | 18:30 24/07",
          "type": "single",
          "display": "thumbnail-only",
          "enable_detail": false,
          "labels": [
            {
              "text": "🕐 Sắp",
              "position": "top-left",
              "color": "#00000080",
              "text_color": "#aaaaaa"
            }
          ],
          "sources": [
            {
              "id": "src-9e78b587fe",
              "name": "GiovangTV",
              "contents": [
                {
                  "id": "ct-9e78b587fe",
                  "name": "Formula 1 vs Belgian Grand Prix 2026",
                  "streams": [
                    {
                      "id": "st-9e78b587fe",
                      "name": "GV",
                      "stream_links": [
                        {
                          "id": "lnk-7dfb9433e6",
                          "name": "Số 7",
                          "type": "hls",
                          "default": true,
                          "url": "https://eqr2hdarxfliv.vcdn.cloud/1784609085_hd/1784609085_hd@720p.m3u8",
                          "request_headers": [
                            {
                              "key": "Referer",
                              "value": "https://giovang.store/"
                            },
                            {
                              "key": "User-Agent",
                              "value": "Mozilla/5.0 (Windows NT 10.0; Win64; x64) AppleWebKit/537.36"
                            }
                          ]
                        }
                      ]
                    }
                  ]
                }
              ]
            }
          ],
          "org_metadata": {
            "league": "Belgian Grand Prix 2026 - F1 Race",
            "team_a": "Formula 1",
            "team_b": "Belgian Grand Prix 2026",
            "logo_a": "https://upload.wikimedia.org/wikipedia/commons/4/45/F1_logo.svg",
            "logo_b": "https://cdn-az.allevents.in/events7/banners/05c379e0-7db7-11f1-8de7-a55c04e17f2e-rimg-w1200-h675-dcf0dbb9-gmir.png?v=1783836045",
            "time": "18:30 24/07",
            "blv": "Số 7",
            "is_live": false,
            "cate_type": "duaxe"
          },
          "image": {
            "padding": 1,
            "background_color": "#ffffff",
            "display": "contain",
            "url": "https://raw.githubusercontent.com/jasminliu98/giovang-stream/refs/heads/main/thumbs/8zsoy5iw2n9q_ecb4e8ea_20260724.png?v=ecb4e8ea",
            "width": 1600,
            "height": 1200
          }
        },
        {
          "id": "gv-6a4e85774d",
          "name": "Formula 1 vs Belgian Grand Prix | 22:00 24/07",
          "type": "single",
          "display": "thumbnail-only",
          "enable_detail": false,
          "labels": [
            {
              "text": "🕐 Sắp",
              "position": "top-left",
              "color": "#00000080",
              "text_color": "#aaaaaa"
            }
          ],
          "sources": [
            {
              "id": "src-6a4e85774d",
              "name": "GiovangTV",
              "contents": [
                {
                  "id": "ct-6a4e85774d",
                  "name": "Formula 1 vs Belgian Grand Prix",
                  "streams": [
                    {
                      "id": "st-6a4e85774d",
                      "name": "GV",
                      "stream_links": [
                        {
                          "id": "lnk-f522a409fb",
                          "name": "Số 7",
                          "type": "hls",
                          "default": true,
                          "url": "https://eqr2hdarxfliv.vcdn.cloud/1784611124_hd/1784611124_hd@720p.m3u8",
                          "request_headers": [
                            {
                              "key": "Referer",
                              "value": "https://giovang.store/"
                            },
                            {
                              "key": "User-Agent",
                              "value": "Mozilla/5.0 (Windows NT 10.0; Win64; x64) AppleWebKit/537.36"
                            }
                          ]
                        }
                      ]
                    }
                  ]
                }
              ]
            }
          ],
          "org_metadata": {
            "league": "F1 Belgian",
            "team_a": "Formula 1",
            "team_b": "Belgian Grand Prix",
            "logo_a": "https://upload.wikimedia.org/wikipedia/commons/4/45/F1_logo.svg",
            "logo_b": "https://cdn-az.allevents.in/events7/banners/05c379e0-7db7-11f1-8de7-a55c04e17f2e-rimg-w1200-h675-dcf0dbb9-gmir.png?v=1783836045",
            "time": "22:00 24/07",
            "blv": "Số 7",
            "is_live": false,
            "cate_type": "duaxe"
          },
          "image": {
            "padding": 1,
            "background_color": "#ffffff",
            "display": "contain",
            "url": "https://raw.githubusercontent.com/jasminliu98/giovang-stream/refs/heads/main/thumbs/ir62tptkknfo_ecb4e8ea_20260724.png?v=ecb4e8ea",
            "width": 1600,
            "height": 1200
          }
        },
        {
          "id": "gv-aae3440e48",
          "name": "Formula 1 vs Belgian Grand Prix | 20:00 26/07",
          "type": "single",
          "display": "thumbnail-only",
          "enable_detail": false,
          "labels": [
            {
              "text": "🕐 Sắp",
              "position": "top-left",
              "color": "#00000080",
              "text_color": "#aaaaaa"
            }
          ],
          "sources": [
            {
              "id": "src-aae3440e48",
              "name": "GiovangTV",
              "contents": [
                {
                  "id": "ct-aae3440e48",
                  "name": "Formula 1 vs Belgian Grand Prix",
                  "streams": [
                    {
                      "id": "st-aae3440e48",
                      "name": "GV",
                      "stream_links": [
                        {
                          "id": "lnk-36941f21ff",
                          "name": "Số 7",
                          "type": "hls",
                          "default": true,
                          "url": "https://eqr2hdarxfliv.vcdn.cloud/1784171115_hd/1784171115_hd@720p.m3u8",
                          "request_headers": [
                            {
                              "key": "Referer",
                              "value": "https://giovang.store/"
                            },
                            {
                              "key": "User-Agent",
                              "value": "Mozilla/5.0 (Windows NT 10.0; Win64; x64) AppleWebKit/537.36"
                            }
                          ]
                        }
                      ]
                    }
                  ]
                }
              ]
            }
          ],
          "org_metadata": {
            "league": "Formula 1",
            "team_a": "Formula 1",
            "team_b": "Belgian Grand Prix",
            "logo_a": "https://upload.wikimedia.org/wikipedia/commons/4/45/F1_logo.svg",
            "logo_b": "https://cdn-az.allevents.in/events7/banners/05c379e0-7db7-11f1-8de7-a55c04e17f2e-rimg-w1200-h675-dcf0dbb9-gmir.png?v=1783836045",
            "time": "20:00 26/07",
            "blv": "Số 7",
            "is_live": false,
            "cate_type": "duaxe"
          },
          "image": {
            "padding": 1,
            "background_color": "#ffffff",
            "display": "contain",
            "url": "https://raw.githubusercontent.com/jasminliu98/giovang-stream/refs/heads/main/thumbs/v5gyjdrrvdtt_ecb4e8ea_20260724.png?v=ecb4e8ea",
            "width": 1600,
            "height": 1200
          }
        }
      ]
    },
    {
      "id": "grp-bóng-bàn",
      "name": "🏓 Bóng Bàn",
      "display": "vertical",
      "grid_number": 2,
      "enable_detail": false,
      "channels": []
    },
    {
      "id": "grp-võ-thuật",
      "name": "🥊 Võ Thuật",
      "display": "vertical",
      "grid_number": 2,
      "enable_detail": false,
      "channels": [
        {
          "id": "gv-f82794c727",
          "name": "ONE Friday Fights 163 vs The Inner Circle 23 | 18:30 24/07",
          "type": "single",
          "display": "thumbnail-only",
          "enable_detail": false,
          "labels": [
            {
              "text": "🕐 Sắp",
              "position": "top-left",
              "color": "#00000080",
              "text_color": "#aaaaaa"
            }
          ],
          "sources": [
            {
              "id": "src-f82794c727",
              "name": "GiovangTV",
              "contents": [
                {
                  "id": "ct-f82794c727",
                  "name": "ONE Friday Fights 163 vs The Inner Circle 23",
                  "streams": [
                    {
                      "id": "st-f82794c727",
                      "name": "GV",
                      "stream_links": [
                        {
                          "id": "lnk-0b84cd0c59",
                          "name": "Số 11",
                          "type": "hls",
                          "default": true,
                          "url": "https://eqr2hdarxfliv.vcdn.cloud/1784611240_hd/1784611240_hd@720p.m3u8",
                          "request_headers": [
                            {
                              "key": "Referer",
                              "value": "https://giovang.store/"
                            },
                            {
                              "key": "User-Agent",
                              "value": "Mozilla/5.0 (Windows NT 10.0; Win64; x64) AppleWebKit/537.36"
                            }
                          ]
                        }
                      ]
                    }
                  ]
                }
              ]
            }
          ],
          "org_metadata": {
            "league": "ONE Friday Fights 163 & The Inner Circle 23",
            "team_a": "ONE Friday Fights 163",
            "team_b": "The Inner Circle 23",
            "logo_a": "https://encrypted-tbn0.gstatic.com/images?q=tbn:ANd9GcReQAGBtiDICY4gh_kkrMENeHVsOldOMBJZx3kszzPpZfeJgUTMIzcMa_4&s=10",
            "logo_b": "https://cdn.onefc.com/wp-content/uploads/2026/05/260724-BKK-OFF163_TIC23-1800x1200px.jpg",
            "time": "18:30 24/07",
            "blv": "Số 11",
            "is_live": false,
            "cate_type": "vothuat"
          },
          "image": {
            "padding": 1,
            "background_color": "#ffffff",
            "display": "contain",
            "url": "https://raw.githubusercontent.com/jasminliu98/giovang-stream/refs/heads/main/thumbs/dtxxrp3lp1af_01b7355b_20260724.png?v=01b7355b",
            "width": 1600,
            "height": 1200
          }
        },
        {
          "id": "gv-9ae1268e24",
          "name": "Ankalaev vs Rountree Jr | 20:00 25/07",
          "type": "single",
          "display": "thumbnail-only",
          "enable_detail": false,
          "labels": [
            {
              "text": "🕐 Sắp",
              "position": "top-left",
              "color": "#00000080",
              "text_color": "#aaaaaa"
            }
          ],
          "sources": [
            {
              "id": "src-9ae1268e24",
              "name": "GiovangTV",
              "contents": [
                {
                  "id": "ct-9ae1268e24",
                  "name": "Ankalaev vs Rountree Jr",
                  "streams": [
                    {
                      "id": "st-9ae1268e24",
                      "name": "GV",
                      "stream_links": [
                        {
                          "id": "lnk-33d3b8ea83",
                          "name": "blv-dory",
                          "type": "httpflv",
                          "default": true,
                          "url": "https://play.megatech.global/live/1783392693_hd@720p.flv",
                          "request_headers": [
                            {
                              "key": "Referer",
                              "value": "https://giovang.store/"
                            },
                            {
                              "key": "User-Agent",
                              "value": "Mozilla/5.0 (Windows NT 10.0; Win64; x64) AppleWebKit/537.36"
                            }
                          ]
                        }
                      ]
                    }
                  ]
                }
              ]
            }
          ],
          "org_metadata": {
            "league": "UFC Fight Night",
            "team_a": "Ankalaev",
            "team_b": "Rountree Jr",
            "logo_a": "https://ufc.com/images/styles/athlete_bio_full_body/s3/2024-10/ANKALAEV_MAGOMED_L_10-26.png?itok=L777PUSb",
            "logo_b": "https://encrypted-tbn0.gstatic.com/images?q=tbn:ANd9GcRVLx-gmgMK6HQ8O-12o4dLil9RM1tl2Q4k0NioC-HW-Q&s=10",
            "time": "20:00 25/07",
            "blv": "blv-dory",
            "is_live": false,
            "cate_type": "vothuat"
          },
          "image": {
            "padding": 1,
            "background_color": "#ffffff",
            "display": "contain",
            "url": "https://raw.githubusercontent.com/jasminliu98/giovang-stream/refs/heads/main/thumbs/ohgm5gr84knm_0c29a9ed_20260724.png?v=0c29a9ed",
            "width": 1600,
            "height": 1200
          }
        },
        {
          "id": "gv-b3ebd7ed3a",
          "name": "Jean vs Musaev | 06:00 26/07",
          "type": "single",
          "display": "thumbnail-only",
          "enable_detail": false,
          "labels": [
            {
              "text": "🕐 Sắp",
              "position": "top-left",
              "color": "#00000080",
              "text_color": "#aaaaaa"
            }
          ],
          "sources": [
            {
              "id": "src-b3ebd7ed3a",
              "name": "GiovangTV",
              "contents": [
                {
                  "id": "ct-b3ebd7ed3a",
                  "name": "Jean vs Musaev",
                  "streams": [
                    {
                      "id": "st-b3ebd7ed3a",
                      "name": "GV",
                      "stream_links": [
                        {
                          "id": "lnk-2f013ee507",
                          "name": "blv-dory",
                          "type": "hls",
                          "default": true,
                          "url": "https://sgtdrxtdjeliv.vcdn.cloud/1783392746_hd/1783392746_hd@720p.m3u8",
                          "request_headers": [
                            {
                              "key": "Referer",
                              "value": "https://giovang.store/"
                            },
                            {
                              "key": "User-Agent",
                              "value": "Mozilla/5.0 (Windows NT 10.0; Win64; x64) AppleWebKit/537.36"
                            }
                          ]
                        }
                      ]
                    }
                  ]
                }
              ]
            }
          ],
          "org_metadata": {
            "league": "PFL Washington DC",
            "team_a": "Jean",
            "team_b": "Musaev",
            "logo_a": "https://encrypted-tbn0.gstatic.com/images?q=tbn:ANd9GcR4CIpcqQny0DLfr0-7zE6HrMbe5mOzUU9r3Y_eitGQkA&s=10",
            "logo_b": "https://encrypted-tbn0.gstatic.com/images?q=tbn:ANd9GcQCKJ0ftySBXWCKiQhX46hGr-gk-8h59Gwf7PfjTgxF0ZoD6k6ujHvlMVAB&s=10",
            "time": "06:00 26/07",
            "blv": "blv-dory",
            "is_live": false,
            "cate_type": "vothuat"
          },
          "image": {
            "padding": 1,
            "background_color": "#ffffff",
            "display": "contain",
            "url": "https://raw.githubusercontent.com/jasminliu98/giovang-stream/refs/heads/main/thumbs/qpb0e45cc7h8_864ca4b3_20260724.png?v=864ca4b3",
            "width": 1600,
            "height": 1200
          }
        }
      ]
    },
    {
      "id": "grp-bóng-chày",
      "name": "⚾ Bóng Chày",
      "display": "vertical",
      "grid_number": 2,
      "enable_detail": false,
      "channels": [
        {
          "id": "gv-f052f387ec",
          "name": "New York Mets vs Los Angeles Dodgers | 06:10 26/07",
          "type": "single",
          "display": "thumbnail-only",
          "enable_detail": false,
          "labels": [
            {
              "text": "🕐 Sắp",
              "position": "top-left",
              "color": "#00000080",
              "text_color": "#aaaaaa"
            }
          ],
          "sources": [
            {
              "id": "src-f052f387ec",
              "name": "GiovangTV",
              "contents": [
                {
                  "id": "ct-f052f387ec",
                  "name": "New York Mets vs Los Angeles Dodgers",
                  "streams": [
                    {
                      "id": "st-f052f387ec",
                      "name": "GV",
                      "stream_links": [
                        {
                          "id": "lnk-a82c257ca1",
                          "name": "Số 7",
                          "type": "hls",
                          "default": true,
                          "url": "https://eqr2hdarxfliv.vcdn.cloud/1784882102_hd/1784882102_hd@720p.m3u8",
                          "request_headers": [
                            {
                              "key": "Referer",
                              "value": "https://giovang.store/"
                            },
                            {
                              "key": "User-Agent",
                              "value": "Mozilla/5.0 (Windows NT 10.0; Win64; x64) AppleWebKit/537.36"
                            }
                          ]
                        }
                      ]
                    }
                  ]
                }
              ]
            }
          ],
          "org_metadata": {
            "league": "MLB",
            "team_a": "New York Mets",
            "team_b": "Los Angeles Dodgers",
            "logo_a": "https://static.flashscore.com/res/image/data/ID1PVAjl-QJ65VxPM.png",
            "logo_b": "https://static.flashscore.com/res/image/data/YeWStKhl-xUjXmOIP.png",
            "time": "06:10 26/07",
            "blv": "Số 7",
            "is_live": false,
            "cate_type": "bongchay"
          },
          "image": {
            "padding": 1,
            "background_color": "#ffffff",
            "display": "contain",
            "url": "https://raw.githubusercontent.com/jasminliu98/giovang-stream/refs/heads/main/thumbs/hg2vop4q3gfe_1fe23eb4_20260724.png?v=1fe23eb4",
            "width": 1600,
            "height": 1200
          }
        }
      ]
    },
    {
      "id": "grp-pickleball",
      "name": "🏸 Pickleball",
      "display": "vertical",
      "grid_number": 2,
      "enable_detail": false,
      "channels": []
    }
  ]
}